{
  "aspace_helpers": [
    {
      "created_at": "2022-04-27T18:51:17",
      "updated_at": "2022-04-27T18:51:17",
      "html_url": "https://github.com/pulibrary/aspace_helpers/pull/204",
      "number": 204,
      "pull_request_html_url": "https://github.com/pulibrary/aspace_helpers/pull/204",
      "repository_html_url": "https://github.com/pulibrary/aspace_helpers",
      "repository_name": "aspace_helpers",
      "state": "open",
      "title": "building a report to find 'Mrs. John Smit'-type names",
      "user_name": "regineheberlein",
      "comments": [],
      "events": [],
      "pr_html_url": "https://github.com/pulibrary/aspace_helpers/pull/204",
      "action": "pull_request_open"
    }
  ],
  "bibdata": [
    {
      "created_at": "2022-04-28T12:27:10",
      "updated_at": "2022-04-28T12:27:10",
      "html_url": "https://github.com/pulibrary/bibdata/pull/1851",
      "number": 1851,
      "pull_request_html_url": "https://github.com/pulibrary/bibdata/pull/1851",
      "repository_html_url": "https://github.com/pulibrary/bibdata",
      "repository_name": "bibdata",
      "state": "closed",
      "title": "Update index manager docs",
      "user_name": "Christina Chortaria",
      "comments": [],
      "events": [
        {
          "actor_name": "Jane Sandberg",
          "created_at": "2022-04-28T15:12:39",
          "type": "referenced"
        },
        {
          "actor_name": "Jane Sandberg",
          "created_at": "2022-04-28T15:12:39",
          "type": "merged"
        },
        {
          "actor_name": "Jane Sandberg",
          "created_at": "2022-04-28T15:12:39",
          "type": "closed"
        },
        {
          "actor_name": "Jane Sandberg",
          "created_at": "2022-04-28T15:12:40",
          "type": "head_ref_deleted"
        }
      ],
      "pr_html_url": "https://github.com/pulibrary/bibdata/pull/1851",
      "action": "pull_request_closed"
    },
    {
      "created_at": "2022-04-25T16:28:33",
      "updated_at": "2022-04-25T16:28:33",
      "html_url": "https://github.com/pulibrary/bibdata/issues/1849",
      "number": 1849,
      "pull_request_html_url": null,
      "repository_html_url": "https://github.com/pulibrary/bibdata",
      "repository_name": "bibdata",
      "state": "open",
      "title": "Consider RES_SHARE$IN_RS_REQ in the availability status response",
      "user_name": "Christina Chortaria",
      "comments": [],
      "events": [
        {
          "actor_name": "Christina Chortaria",
          "created_at": "2022-04-28T15:22:01",
          "type": "assigned"
        }
      ],
      "pr_html_url": null,
      "action": "updated"
    }
  ],
  "dspace-development": [
    {
      "created_at": "2022-03-22T20:17:25",
      "updated_at": "2022-03-22T20:17:25",
      "html_url": "https://github.com/pulibrary/dspace-development/issues/619",
      "number": 619,
      "pull_request_html_url": null,
      "repository_html_url": "https://github.com/pulibrary/dspace-development",
      "repository_name": "dspace-development",
      "state": "open",
      "title": "Symplectic Elements: Searching queues seem frozen",
      "user_name": "Hannah H",
      "comments": [
        {
          "user_name": "James R. Griffin III",
          "updated_at": "2022-04-28T18:35:34",
          "html_url": "https://github.com/pulibrary/dspace-development/issues/619#issuecomment-1112535928",
          "body": "After a brief pairing session with Symplectic Support, it was discovered that there are database connectivity issues affecting the server for Elements:\n\n```powershell\n2022-04-28 14:07:48: Exception on machine: NetBIOS name \"CISDR201W\", OS \"Microsoft Windows NT 6.2.9200.0\" (64-bit)\nSoftware instance: Default, Software Version: 5.14.0.2013, Commit Hash: b1ac109d2f78883a8ae8ff767c364b06b3cb9dc8\nCommand \"\"D:\\Symplectic\\Elements\\Scheduler.Service\\Scheduler.Service.exe\"\" (32-bit)\n-----------------------------------------------------------------------------------\nLog entry ID: fb9d958e-e209-489d-9eec-00057fe26179\nLogged at: 14:07:48.941 28/04/22\n\nLevel 1:\n-------\nException type: System.Data.SqlClient.SqlException\nMessage: A network-related or instance-specific error occurred while establishing a connection to SQL Server. The server was not found or was not accessible. Verify that the instance name is correct and that SQL Server is configured to allow remote connections. (provider: Named Pipes Provider, error: 40 - Could not open a connection to SQL Server)\nStack trace:\nat System.Data.SqlClient.SqlInternalConnectionTds..ctor(DbConnectionPoolIdentity, SqlConnectionString, SqlCredential, Object, String, SecureString, Boolean, SqlConnectionString, SessionData, DbConnectionPool, String, Boolean, SqlAuthenticationProviderManager)\nat System.Data.SqlClient.SqlConnectionFactory.CreateConnection(DbConnectionOptions, DbConnectionPoolKey, Object, DbConnectionPool, DbConnection, DbConnectionOptions)\nat System.Data.ProviderBase.DbConnectionFactory.CreatePooledConnection(DbConnectionPool, DbConnection, DbConnectionOptions, DbConnectionPoolKey, DbConnectionOptions)\nat System.Data.ProviderBase.DbConnectionPool.CreateObject(DbConnection, DbConnectionOptions, DbConnectionInternal)\nat System.Data.ProviderBase.DbConnectionPool.UserCreateRequest(DbConnection, DbConnectionOptions, DbConnectionInternal)\nat System.Data.ProviderBase.DbConnectionPool.TryGetConnection(DbConnection, UInt32, Boolean, Boolean, DbConnectionOptions, DbConnectionInternal&)\nat System.Data.ProviderBase.DbConnectionPool.TryGetConnection(DbConnection, TaskCompletionSource<DbConnectionInternal>, DbConnectionOptions, DbConnectionInternal&)\nat System.Data.ProviderBase.DbConnectionFactory.TryGetConnection(DbConnection, TaskCompletionSource<DbConnectionInternal>, DbConnectionOptions, DbConnectionInternal, DbConnectionInternal&)\nat System.Data.ProviderBase.DbConnectionInternal.TryOpenConnectionInternal(DbConnection, DbConnectionFactory, TaskCompletionSource<DbConnectionInternal>, DbConnectionOptions)\nat System.Data.ProviderBase.DbConnectionClosed.TryOpenConnection(DbConnection, DbConnectionFactory, TaskCompletionSource<DbConnectionInternal>, DbConnectionOptions)\nat System.Data.SqlClient.SqlConnection.TryOpenInner(TaskCompletionSource<DbConnectionInternal>)\nat System.Data.SqlClient.SqlConnection.TryOpen(TaskCompletionSource<DbConnectionInternal>)\nat System.Data.SqlClient.SqlConnection.Open()\nat Symplectic.Data.TransactionManager.NewScope(Boolean, Boolean, Nullable<IsolationLevel>) in libraries\\Symplectic.Data\\GenericTransactionManager.cs:line 224, char 6\nat Symplectic.Data.GenericTransactionManager<N, C, A, R, T>.ExecuteReader(C, CommandBehavior, Action) in libraries\\Symplectic.Data\\GenericTransactionManager.cs:line 932, char 4\nat Symplectic.Elements.DataAccess.ElementsDatabase.GetJobs(Nullable<Int32>) in elements\\DataAccess\\ElementsDatabase.cs:line 383, char 4\nat Symplectic.Elements.DataAccess.ElementsDatabase.GetAllJobSchedules() in elements\\DataAccess\\ElementsDatabase.cs:line 365, char 31\nat Symplectic.Elements.Scheduler.Service.Scheduler.UpdateSchedule(OperationSource) in elements\\Scheduler.Service\\Scheduler.cs:line 208, char 6\nat Symplectic.Elements.Scheduler.Service.Scheduler.MainTimerTick(Object) in elements\\Scheduler.Service\\Scheduler.cs:line 867, char 5\n\nSQL-specific information:\n\nSQL Error:\n\tClass: 20\n\tNumber: 53\n\tState: 0\n\tProvider: .Net SqlClient Data Provider\n\tServer: \n\tProcedure: \n\tLine number: 0\n\nLevel 2:\n-------\nException type: System.ComponentModel.Win32Exception\nMessage: The network path was not found\nException not yet thrown.\n```"
        },
        {
          "user_name": "James R. Griffin III",
          "updated_at": "2022-04-28T18:37:50",
          "html_url": "https://github.com/pulibrary/dspace-development/issues/619#issuecomment-1112537758",
          "body": "In response to this, I am afraid that I am going to need to submit a SN@P support request to try and diagnose the database connectivity issues with the OIT."
        },
        {
          "user_name": "James R. Griffin III",
          "updated_at": "2022-04-28T18:46:45",
          "html_url": "https://github.com/pulibrary/dspace-development/issues/619#issuecomment-1112544820",
          "body": "This is now being tracked with https://princeton.service-now.com/now/workspace/agent/record/incident/6406ee4f874f0d1452d1edfd0ebb3599"
        },
        {
          "user_name": "James R. Griffin III",
          "updated_at": "2022-04-28T18:46:46",
          "html_url": "https://github.com/pulibrary/dspace-development/issues/619#issuecomment-1112544826",
          "body": "This is now being tracked with https://princeton.service-now.com/now/workspace/agent/record/incident/6406ee4f874f0d1452d1edfd0ebb3599"
        }
      ],
      "events": [],
      "pr_html_url": null,
      "action": "updated"
    }
  ],
  "figgy": [
    {
      "created_at": "2022-04-28T15:34:35",
      "updated_at": "2022-04-28T15:34:35",
      "html_url": "https://github.com/pulibrary/figgy/pull/5097",
      "number": 5097,
      "pull_request_html_url": "https://github.com/pulibrary/figgy/pull/5097",
      "repository_html_url": "https://github.com/pulibrary/figgy",
      "repository_name": "figgy",
      "state": "closed",
      "title": "Update Embed graphql schema to send type and content",
      "user_name": "hackartisan",
      "comments": [],
      "events": [
        {
          "actor_name": "Trey Pendragon",
          "created_at": "2022-04-28T16:06:48",
          "type": "referenced"
        },
        {
          "actor_name": "Trey Pendragon",
          "created_at": "2022-04-28T16:06:48",
          "type": "merged"
        },
        {
          "actor_name": "Trey Pendragon",
          "created_at": "2022-04-28T16:06:48",
          "type": "closed"
        },
        {
          "actor_name": "Trey Pendragon",
          "created_at": "2022-04-28T16:06:49",
          "type": "head_ref_deleted"
        }
      ],
      "pr_html_url": "https://github.com/pulibrary/figgy/pull/5097",
      "action": "pull_request_closed"
    },
    {
      "created_at": "2021-10-01T19:35:01",
      "updated_at": "2021-10-01T19:35:01",
      "html_url": "https://github.com/pulibrary/figgy/issues/4690",
      "number": 4690,
      "pull_request_html_url": null,
      "repository_html_url": "https://github.com/pulibrary/figgy",
      "repository_name": "figgy",
      "state": "open",
      "title": "Alma Synchronization is broken.",
      "user_name": "Trey Pendragon",
      "comments": [
        {
          "user_name": "hackartisan",
          "updated_at": "2022-04-28T17:47:28",
          "html_url": "https://github.com/pulibrary/figgy/issues/4690#issuecomment-1112491411",
          "body": "related to #4774\r\n\r\ndocument: https://docs.google.com/document/d/1Qx4orfeorpJlkupA-jfZsY-0bPM0xolaEGrh1zpbBUY/edit#"
        }
      ],
      "events": [],
      "pr_html_url": null,
      "action": "updated"
    },
    {
      "created_at": "2021-11-05T19:52:46",
      "updated_at": "2021-11-05T19:52:46",
      "html_url": "https://github.com/pulibrary/figgy/issues/4774",
      "number": 4774,
      "pull_request_html_url": null,
      "repository_html_url": "https://github.com/pulibrary/figgy",
      "repository_name": "figgy",
      "state": "open",
      "title": "Resources updated in Pulfalight should update their metadata in Figgy automatically.",
      "user_name": "Trey Pendragon",
      "comments": [
        {
          "user_name": "hackartisan",
          "updated_at": "2022-04-28T18:01:19",
          "html_url": "https://github.com/pulibrary/figgy/issues/4774#issuecomment-1112506138",
          "body": "endpoint `/resources/update_metadata` expects a body like `{ source_metadata_identifiers: [...] }` or `{ archival_collection_codes: [...] }`. For this ticket implement the code path for `archival_collection_codes`.\r\n\r\nImplementation\r\n\r\n- I get a list of things\r\n- I kick of a job for each thing in the list\r\n- That spawns a job per figgy resource that actually fetches the record/s from pulfalight\r\n- See if metadata changed somehow before we persist to prevent needlessly re-preserving.\r\n  - Note that the source metadata sync happens in the change set persister; we would have to compare up front somehow\r\n- Use batches?\r\n  - Would let us see the hierarchy of these jobs.\r\n\r\nExample:\r\n\r\n- I update C0001_c01 in ASpace\r\n- Pulfalight hears that C001 changed.\r\n- Pulfalight reindexes the full collection, because it has to, that’s how Pulfalight works.\r\n- Pulfalight posts to figgy /resources/update_metadata with body { archival_collection_codes: [“C0001”] }\r\n- Figgy hears the request, spawns a job for updating per collection code, returns “202 Accepted”.\r\n  - queue low priority\r\n- That job gets all resources which have that archival collection code, and spawns a metadata refresh job for each of those resources.\r\n- The metadata refresh job should try to update, if nothing changes then don’t persist.\r\n  - This metadata refresh job should be in the low priority queue.\r\n- How many jobs per metadata update?\r\n  - End up with one job per resource to be updated."
        }
      ],
      "events": [],
      "pr_html_url": null,
      "action": "updated"
    }
  ],
  "lib_jobs": [
    {
      "created_at": "2022-04-27T13:58:59",
      "updated_at": "2022-04-27T13:58:59",
      "html_url": "https://github.com/pulibrary/lib_jobs/pull/300",
      "number": 300,
      "pull_request_html_url": "https://github.com/pulibrary/lib_jobs/pull/300",
      "repository_html_url": "https://github.com/pulibrary/lib_jobs",
      "repository_name": "lib_jobs",
      "state": "open",
      "title": "Adding in NCIP renewal",
      "user_name": "carolyncole",
      "comments": [],
      "events": [],
      "pr_html_url": "https://github.com/pulibrary/lib_jobs/pull/300",
      "action": "pull_request_open"
    }
  ],
  "lux": [
    {
      "created_at": "2022-04-28T20:35:15",
      "updated_at": "2022-04-28T20:35:15",
      "html_url": "https://github.com/pulibrary/lux/pull/390",
      "number": 390,
      "pull_request_html_url": "https://github.com/pulibrary/lux/pull/390",
      "repository_html_url": "https://github.com/pulibrary/lux",
      "repository_name": "lux",
      "state": "open",
      "title": "Bump async from 2.6.3 to 2.6.4",
      "user_name": "dependabot[bot]",
      "comments": [],
      "events": [
        {
          "actor_name": null,
          "created_at": "2022-04-28T20:35:16",
          "type": "labeled"
        }
      ],
      "pr_html_url": "https://github.com/pulibrary/lux/pull/390",
      "action": "pull_request_open"
    }
  ],
  "orangelight": [
    {
      "created_at": "2022-03-22T15:26:13",
      "updated_at": "2022-03-22T15:26:13",
      "html_url": "https://github.com/pulibrary/orangelight/pull/2903",
      "number": 2903,
      "pull_request_html_url": "https://github.com/pulibrary/orangelight/pull/2903",
      "repository_html_url": "https://github.com/pulibrary/orangelight",
      "repository_name": "orangelight",
      "state": "closed",
      "title": "Adding alma as a login option",
      "user_name": "carolyncole",
      "comments": [
        {
          "user_name": "Coveralls",
          "updated_at": "2022-04-28T13:41:46",
          "html_url": "https://github.com/pulibrary/orangelight/pull/2903#issuecomment-1089243985",
          "body": "\n[![Coverage Status](https://coveralls.io/builds/48663891/badge)](https://coveralls.io/builds/48663891)\n\nCoverage decreased (-0.3%) to 94.189% when pulling **c44a159cea5d905d30af109962c29faa6242ca66 on i2846-alma-login** into **06d46bf7096ce4f1a04a772c5584b896884b58c6 on main**.\n"
        }
      ],
      "events": [
        {
          "actor_name": null,
          "created_at": "2022-04-28T13:27:31",
          "type": "head_ref_force_pushed"
        },
        {
          "actor_name": null,
          "created_at": "2022-04-28T13:31:12",
          "type": "head_ref_force_pushed"
        },
        {
          "actor_name": null,
          "created_at": "2022-04-28T13:35:31",
          "type": "ready_for_review"
        },
        {
          "actor_name": "Jane Sandberg",
          "created_at": "2022-04-28T15:19:30",
          "type": "referenced"
        },
        {
          "actor_name": "Jane Sandberg",
          "created_at": "2022-04-28T15:19:30",
          "type": "merged"
        },
        {
          "actor_name": "Jane Sandberg",
          "created_at": "2022-04-28T15:19:30",
          "type": "closed"
        },
        {
          "actor_name": "Jane Sandberg",
          "created_at": "2022-04-28T15:19:31",
          "type": "head_ref_deleted"
        }
      ],
      "pr_html_url": "https://github.com/pulibrary/orangelight/pull/2903",
      "action": "pull_request_closed"
    },
    {
      "created_at": "2022-04-28T12:16:23",
      "updated_at": "2022-04-28T12:16:23",
      "html_url": "https://github.com/pulibrary/orangelight/pull/2971",
      "number": 2971,
      "pull_request_html_url": "https://github.com/pulibrary/orangelight/pull/2971",
      "repository_html_url": "https://github.com/pulibrary/orangelight",
      "repository_name": "orangelight",
      "state": "open",
      "title": "Items in firestone$pf have pickup microforms",
      "user_name": "Christina Chortaria",
      "comments": [
        {
          "user_name": "Coveralls",
          "updated_at": "2022-04-29T00:26:51",
          "html_url": "https://github.com/pulibrary/orangelight/pull/2971#issuecomment-1112773004",
          "body": "\n[![Coverage Status](https://coveralls.io/builds/48686915/badge)](https://coveralls.io/builds/48686915)\n\nCoverage decreased (-0.01%) to 94.176% when pulling **e60b1236fb08d26171e311bbcefbc813c3e6c2e1 on 2934-request-form-display-pf** into **a159febd4219e154e16da63c6ef1fd4dd057c749 on main**.\n"
        }
      ],
      "events": [
        {
          "actor_name": "Christina Chortaria",
          "created_at": "2022-04-28T12:35:15",
          "type": "head_ref_force_pushed"
        },
        {
          "actor_name": "Christina Chortaria",
          "created_at": "2022-04-28T17:30:07",
          "type": "head_ref_force_pushed"
        },
        {
          "actor_name": null,
          "created_at": "2022-04-28T17:30:52",
          "type": "deployed"
        },
        {
          "actor_name": "Christina Chortaria",
          "created_at": "2022-04-28T18:31:23",
          "type": "head_ref_force_pushed"
        },
        {
          "actor_name": null,
          "created_at": "2022-04-28T18:37:36",
          "type": "deployed"
        },
        {
          "actor_name": "Christina Chortaria",
          "created_at": "2022-04-28T20:17:00",
          "type": "head_ref_force_pushed"
        },
        {
          "actor_name": "Christina Chortaria",
          "created_at": "2022-04-29T00:08:40",
          "type": "head_ref_force_pushed"
        },
        {
          "actor_name": "Christina Chortaria",
          "created_at": "2022-04-29T00:12:55",
          "type": "head_ref_force_pushed"
        },
        {
          "actor_name": "Christina Chortaria",
          "created_at": "2022-04-29T00:19:23",
          "type": "head_ref_force_pushed"
        }
      ],
      "pr_html_url": "https://github.com/pulibrary/orangelight/pull/2971",
      "action": "pull_request_open"
    }
  ],
  "pdc_describe": [
    {
      "created_at": "2022-03-30T13:33:00",
      "updated_at": "2022-03-30T13:33:00",
      "html_url": "https://github.com/pulibrary/pdc_describe/issues/39",
      "number": 39,
      "pull_request_html_url": null,
      "repository_html_url": "https://github.com/pulibrary/pdc_describe",
      "repository_name": "pdc_describe",
      "state": "closed",
      "title": "Increase the test code coverage to 100%",
      "user_name": "James R. Griffin III",
      "comments": [],
      "events": [
        {
          "actor_name": "Bess Sadler",
          "created_at": "2022-04-28T17:02:27",
          "type": "closed"
        }
      ],
      "pr_html_url": null,
      "action": "closed"
    },
    {
      "created_at": "2022-04-27T15:56:38",
      "updated_at": "2022-04-27T15:56:38",
      "html_url": "https://github.com/pulibrary/pdc_describe/pull/85",
      "number": 85,
      "pull_request_html_url": "https://github.com/pulibrary/pdc_describe/pull/85",
      "repository_html_url": "https://github.com/pulibrary/pdc_describe",
      "repository_name": "pdc_describe",
      "state": "closed",
      "title": "Increasing the test coverage to meet 100%",
      "user_name": "James R. Griffin III",
      "comments": [],
      "events": [
        {
          "actor_name": "Bess Sadler",
          "created_at": "2022-04-28T17:02:27",
          "type": "referenced"
        },
        {
          "actor_name": "Bess Sadler",
          "created_at": "2022-04-28T17:02:27",
          "type": "merged"
        },
        {
          "actor_name": "Bess Sadler",
          "created_at": "2022-04-28T17:02:27",
          "type": "closed"
        },
        {
          "actor_name": "Bess Sadler",
          "created_at": "2022-04-28T17:02:28",
          "type": "head_ref_deleted"
        }
      ],
      "pr_html_url": "https://github.com/pulibrary/pdc_describe/pull/85",
      "action": "pull_request_closed"
    },
    {
      "created_at": "2022-04-28T16:58:18",
      "updated_at": "2022-04-28T16:58:18",
      "html_url": "https://github.com/pulibrary/pdc_describe/pull/87",
      "number": 87,
      "pull_request_html_url": "https://github.com/pulibrary/pdc_describe/pull/87",
      "repository_html_url": "https://github.com/pulibrary/pdc_describe",
      "repository_name": "pdc_describe",
      "state": "closed",
      "title": "Upgrade to postgres 13 to match server",
      "user_name": "Bess Sadler",
      "comments": [],
      "events": [
        {
          "actor_name": "Bess Sadler",
          "created_at": "2022-04-28T17:04:27",
          "type": "convert_to_draft"
        },
        {
          "actor_name": "Bess Sadler",
          "created_at": "2022-04-28T17:06:35",
          "type": "ready_for_review"
        },
        {
          "actor_name": "Kate Lynch",
          "created_at": "2022-04-28T17:43:26",
          "type": "assigned"
        },
        {
          "actor_name": "Kate Lynch",
          "created_at": "2022-04-28T17:43:41",
          "type": "referenced"
        },
        {
          "actor_name": "Kate Lynch",
          "created_at": "2022-04-28T17:43:41",
          "type": "merged"
        },
        {
          "actor_name": "Kate Lynch",
          "created_at": "2022-04-28T17:43:41",
          "type": "closed"
        },
        {
          "actor_name": "Kate Lynch",
          "created_at": "2022-04-28T17:43:41",
          "type": "head_ref_deleted"
        }
      ],
      "pr_html_url": "https://github.com/pulibrary/pdc_describe/pull/87",
      "action": "pull_request_closed"
    },
    {
      "created_at": "2022-04-25T15:00:10",
      "updated_at": "2022-04-25T15:00:10",
      "html_url": "https://github.com/pulibrary/pdc_describe/issues/83",
      "number": 83,
      "pull_request_html_url": null,
      "repository_html_url": "https://github.com/pulibrary/pdc_describe",
      "repository_name": "pdc_describe",
      "state": "open",
      "title": "Make fixtures for research data",
      "user_name": "Kate Lynch",
      "comments": [],
      "events": [
        {
          "actor_name": "James R. Griffin III",
          "created_at": "2022-04-28T17:44:17",
          "type": "unassigned"
        },
        {
          "actor_name": "Kate Lynch",
          "created_at": "2022-04-28T17:44:18",
          "type": "assigned"
        }
      ],
      "pr_html_url": null,
      "action": "updated"
    },
    {
      "created_at": "2022-03-22T13:36:38",
      "updated_at": "2022-03-22T13:36:38",
      "html_url": "https://github.com/pulibrary/pdc_describe/issues/17",
      "number": 17,
      "pull_request_html_url": null,
      "repository_html_url": "https://github.com/pulibrary/pdc_describe",
      "repository_name": "pdc_describe",
      "state": "open",
      "title": "DataCite - Using an existing ARK updates the ezid metadata",
      "user_name": "Bess Sadler",
      "comments": [],
      "events": [
        {
          "actor_name": "Hector Correa",
          "created_at": "2022-04-28T19:21:47",
          "type": "assigned"
        },
        {
          "actor_name": "Hector Correa",
          "created_at": "2022-04-28T19:23:16",
          "type": "unassigned"
        }
      ],
      "pr_html_url": null,
      "action": "updated"
    },
    {
      "created_at": "2022-04-27T20:48:33",
      "updated_at": "2022-04-27T20:48:33",
      "html_url": "https://github.com/pulibrary/pdc_describe/pull/86",
      "number": 86,
      "pull_request_html_url": "https://github.com/pulibrary/pdc_describe/pull/86",
      "repository_html_url": "https://github.com/pulibrary/pdc_describe",
      "repository_name": "pdc_describe",
      "state": "closed",
      "title": "Collection management",
      "user_name": "Hector Correa",
      "comments": [],
      "events": [
        {
          "actor_name": "Hector Correa",
          "created_at": "2022-04-28T18:14:15",
          "type": "renamed"
        },
        {
          "actor_name": "Hector Correa",
          "created_at": "2022-04-28T18:21:12",
          "type": "ready_for_review"
        },
        {
          "actor_name": "Bess Sadler",
          "created_at": "2022-04-28T19:56:39",
          "type": "referenced"
        },
        {
          "actor_name": "Bess Sadler",
          "created_at": "2022-04-28T19:56:39",
          "type": "merged"
        },
        {
          "actor_name": "Bess Sadler",
          "created_at": "2022-04-28T19:56:39",
          "type": "closed"
        },
        {
          "actor_name": "Bess Sadler",
          "created_at": "2022-04-28T19:56:39",
          "type": "head_ref_deleted"
        }
      ],
      "pr_html_url": "https://github.com/pulibrary/pdc_describe/pull/86",
      "action": "pull_request_closed"
    },
    {
      "created_at": "2022-04-22T17:51:19",
      "updated_at": "2022-04-22T17:51:19",
      "html_url": "https://github.com/pulibrary/pdc_describe/issues/78",
      "number": 78,
      "pull_request_html_url": null,
      "repository_html_url": "https://github.com/pulibrary/pdc_describe",
      "repository_name": "pdc_describe",
      "state": "open",
      "title": "Display file metadata on dataset show page",
      "user_name": "Bess Sadler",
      "comments": [
        {
          "user_name": "Bess Sadler",
          "updated_at": "2022-04-28T20:02:27",
          "html_url": "https://github.com/pulibrary/pdc_describe/issues/78#issuecomment-1112604757",
          "body": "![Screen Shot 2022-04-28 at 3 41 45 PM](https://user-images.githubusercontent.com/65608/165836076-36ea5216-328b-493f-91d8-8814025d2786.png)\r\n"
        }
      ],
      "events": [],
      "pr_html_url": null,
      "action": "updated"
    },
    {
      "created_at": "2022-04-28T18:45:20",
      "updated_at": "2022-04-28T18:45:20",
      "html_url": "https://github.com/pulibrary/pdc_describe/pull/88",
      "number": 88,
      "pull_request_html_url": "https://github.com/pulibrary/pdc_describe/pull/88",
      "repository_html_url": "https://github.com/pulibrary/pdc_describe",
      "repository_name": "pdc_describe",
      "state": "closed",
      "title": "Show files in S3 on dataset show page",
      "user_name": "Bess Sadler",
      "comments": [
        {
          "user_name": "Bess Sadler",
          "updated_at": "2022-04-28T19:42:21",
          "html_url": "https://github.com/pulibrary/pdc_describe/pull/88#issuecomment-1112589532",
          "body": "![Screen Shot 2022-04-28 at 3 41 45 PM](https://user-images.githubusercontent.com/65608/165832913-2a5f2648-af48-4195-98e3-5b62b1365168.png)\r\n"
        }
      ],
      "events": [
        {
          "actor_name": "Bess Sadler",
          "created_at": "2022-04-28T18:47:11",
          "type": "head_ref_force_pushed"
        },
        {
          "actor_name": "Hector Correa",
          "created_at": "2022-04-28T20:13:23",
          "type": "referenced"
        },
        {
          "actor_name": "Hector Correa",
          "created_at": "2022-04-28T20:13:23",
          "type": "merged"
        },
        {
          "actor_name": "Hector Correa",
          "created_at": "2022-04-28T20:13:23",
          "type": "closed"
        },
        {
          "actor_name": "Hector Correa",
          "created_at": "2022-04-28T20:13:23",
          "type": "head_ref_deleted"
        }
      ],
      "pr_html_url": "https://github.com/pulibrary/pdc_describe/pull/88",
      "action": "pull_request_closed"
    },
    {
      "created_at": "2022-03-21T20:51:26",
      "updated_at": "2022-03-21T20:51:26",
      "html_url": "https://github.com/pulibrary/pdc_describe/issues/12",
      "number": 12,
      "pull_request_html_url": null,
      "repository_html_url": "https://github.com/pulibrary/pdc_describe",
      "repository_name": "pdc_describe",
      "state": "open",
      "title": "DataCite based input form",
      "user_name": "Bess Sadler",
      "comments": [
        {
          "user_name": "Hannah H",
          "updated_at": "2022-04-28T20:16:15",
          "html_url": "https://github.com/pulibrary/pdc_describe/issues/12#issuecomment-1112615622",
          "body": "@hectorcorrea PRDS is in the process of deciding on the Datacite (4.4) fields to put into this form. I expect to have this for you in a spreadsheet sometime next week. The current schema is Datacite 4.4 and here is the link: https://schema.datacite.org/meta/kernel-4.4/"
        }
      ],
      "events": [
        {
          "actor_name": "Hector Correa",
          "created_at": "2022-04-28T19:23:02",
          "type": "assigned"
        },
        {
          "actor_name": "Hector Correa",
          "created_at": "2022-04-28T20:16:15",
          "type": "mentioned"
        },
        {
          "actor_name": "Hector Correa",
          "created_at": "2022-04-28T20:16:15",
          "type": "subscribed"
        }
      ],
      "pr_html_url": null,
      "action": "updated"
    },
    {
      "created_at": "2022-04-28T20:46:50",
      "updated_at": "2022-04-28T20:46:50",
      "html_url": "https://github.com/pulibrary/pdc_describe/issues/89",
      "number": 89,
      "pull_request_html_url": null,
      "repository_html_url": "https://github.com/pulibrary/pdc_describe",
      "repository_name": "pdc_describe",
      "state": "open",
      "title": "Collection Show page and superadmins",
      "user_name": "Hector Correa",
      "comments": [],
      "events": [],
      "pr_html_url": null,
      "action": "created"
    },
    {
      "created_at": "2022-04-28T20:49:22",
      "updated_at": "2022-04-28T20:49:22",
      "html_url": "https://github.com/pulibrary/pdc_describe/issues/90",
      "number": 90,
      "pull_request_html_url": null,
      "repository_html_url": "https://github.com/pulibrary/pdc_describe",
      "repository_name": "pdc_describe",
      "state": "open",
      "title": "Login process and default_collection",
      "user_name": "Hector Correa",
      "comments": [],
      "events": [
        {
          "actor_name": "Hector Correa",
          "created_at": "2022-04-28T20:49:25",
          "type": "assigned"
        }
      ],
      "pr_html_url": null,
      "action": "created"
    },
    {
      "created_at": "2022-04-28T21:00:39",
      "updated_at": "2022-04-28T21:00:39",
      "html_url": "https://github.com/pulibrary/pdc_describe/pull/91",
      "number": 91,
      "pull_request_html_url": "https://github.com/pulibrary/pdc_describe/pull/91",
      "repository_html_url": "https://github.com/pulibrary/pdc_describe",
      "repository_name": "pdc_describe",
      "state": "open",
      "title": "83 fixtures for research data",
      "user_name": "Kate Lynch",
      "comments": [],
      "events": [],
      "pr_html_url": "https://github.com/pulibrary/pdc_describe/pull/91",
      "action": "pull_request_open"
    },
    {
      "created_at": "2022-04-28T21:13:22",
      "updated_at": "2022-04-28T21:13:22",
      "html_url": "https://github.com/pulibrary/pdc_describe/pull/92",
      "number": 92,
      "pull_request_html_url": "https://github.com/pulibrary/pdc_describe/pull/92",
      "repository_html_url": "https://github.com/pulibrary/pdc_describe",
      "repository_name": "pdc_describe",
      "state": "open",
      "title": "Implements support for importing Dublin Core metadata into Works from the OAI-PMH (for handling Library PDF Items in DataSpace)",
      "user_name": "James R. Griffin III",
      "comments": [],
      "events": [],
      "pr_html_url": "https://github.com/pulibrary/pdc_describe/pull/92",
      "action": "pull_request_open"
    }
  ],
  "princeton_ansible": [
    {
      "created_at": "2022-04-28T14:09:10",
      "updated_at": "2022-04-28T14:09:10",
      "html_url": "https://github.com/pulibrary/princeton_ansible/pull/2999",
      "number": 2999,
      "pull_request_html_url": "https://github.com/pulibrary/princeton_ansible/pull/2999",
      "repository_html_url": "https://github.com/pulibrary/princeton_ansible",
      "repository_name": "princeton_ansible",
      "state": "closed",
      "title": "Offboard Xander",
      "user_name": "hackartisan",
      "comments": [],
      "events": [
        {
          "actor_name": "Eliot Jordan",
          "created_at": "2022-04-28T14:57:51",
          "type": "referenced"
        },
        {
          "actor_name": "Eliot Jordan",
          "created_at": "2022-04-28T14:57:51",
          "type": "merged"
        },
        {
          "actor_name": "Eliot Jordan",
          "created_at": "2022-04-28T14:57:51",
          "type": "closed"
        },
        {
          "actor_name": "Eliot Jordan",
          "created_at": "2022-04-28T14:57:52",
          "type": "head_ref_deleted"
        }
      ],
      "pr_html_url": "https://github.com/pulibrary/princeton_ansible/pull/2999",
      "action": "pull_request_closed"
    },
    {
      "created_at": "2022-04-27T19:38:37",
      "updated_at": "2022-04-27T19:38:37",
      "html_url": "https://github.com/pulibrary/princeton_ansible/pull/2996",
      "number": 2996,
      "pull_request_html_url": "https://github.com/pulibrary/princeton_ansible/pull/2996",
      "repository_html_url": "https://github.com/pulibrary/princeton_ansible",
      "repository_name": "princeton_ansible",
      "state": "closed",
      "title": "Add datadog to lib-jobs",
      "user_name": "Jane Sandberg",
      "comments": [
        {
          "user_name": "Jane Sandberg",
          "updated_at": "2022-04-27T22:35:55",
          "html_url": "https://github.com/pulibrary/princeton_ansible/pull/2996#issuecomment-1111546116",
          "body": "I ran this playbook earlier today, and it did the trick.  Just rebased in the hopes that CI would be happier. :-)"
        }
      ],
      "events": [
        {
          "actor_name": "Jane Sandberg",
          "created_at": "2022-04-27T22:34:06",
          "type": "head_ref_force_pushed"
        },
        {
          "actor_name": "Jane Sandberg",
          "created_at": "2022-04-27T22:34:26",
          "type": "ready_for_review"
        },
        {
          "actor_name": "Christina Chortaria",
          "created_at": "2022-04-28T15:02:13",
          "type": "referenced"
        },
        {
          "actor_name": "Christina Chortaria",
          "created_at": "2022-04-28T15:02:13",
          "type": "merged"
        },
        {
          "actor_name": "Christina Chortaria",
          "created_at": "2022-04-28T15:02:14",
          "type": "closed"
        },
        {
          "actor_name": "Christina Chortaria",
          "created_at": "2022-04-28T15:02:15",
          "type": "head_ref_deleted"
        }
      ],
      "pr_html_url": "https://github.com/pulibrary/princeton_ansible/pull/2996",
      "action": "pull_request_closed"
    },
    {
      "created_at": "2022-04-27T21:10:39",
      "updated_at": "2022-04-27T21:10:39",
      "html_url": "https://github.com/pulibrary/princeton_ansible/pull/2997",
      "number": 2997,
      "pull_request_html_url": "https://github.com/pulibrary/princeton_ansible/pull/2997",
      "repository_html_url": "https://github.com/pulibrary/princeton_ansible",
      "repository_name": "princeton_ansible",
      "state": "open",
      "title": "Rotate logs on bibdata-alma-workers boxes",
      "user_name": "Alicia Cozine",
      "comments": [],
      "events": [],
      "pr_html_url": "https://github.com/pulibrary/princeton_ansible/pull/2997",
      "action": "pull_request_open"
    },
    {
      "created_at": "2022-04-28T19:03:05",
      "updated_at": "2022-04-28T19:03:05",
      "html_url": "https://github.com/pulibrary/princeton_ansible/issues/3003",
      "number": 3003,
      "pull_request_html_url": null,
      "repository_html_url": "https://github.com/pulibrary/princeton_ansible",
      "repository_name": "princeton_ansible",
      "state": "open",
      "title": "Re-key vaulted vars",
      "user_name": "Alicia Cozine",
      "comments": [],
      "events": [],
      "pr_html_url": null,
      "action": "created"
    },
    {
      "created_at": "2022-04-28T14:51:24",
      "updated_at": "2022-04-28T14:51:24",
      "html_url": "https://github.com/pulibrary/princeton_ansible/pull/3000",
      "number": 3000,
      "pull_request_html_url": "https://github.com/pulibrary/princeton_ansible/pull/3000",
      "repository_html_url": "https://github.com/pulibrary/princeton_ansible",
      "repository_name": "princeton_ansible",
      "state": "closed",
      "title": "manage ssh keys",
      "user_name": "Francis Kayiwa",
      "comments": [],
      "events": [
        {
          "actor_name": "Francis Kayiwa",
          "created_at": "2022-04-28T14:51:48",
          "type": "review_requested"
        },
        {
          "actor_name": "Alicia Cozine",
          "created_at": "2022-04-28T19:56:27",
          "type": "referenced"
        },
        {
          "actor_name": "Alicia Cozine",
          "created_at": "2022-04-28T19:56:28",
          "type": "merged"
        },
        {
          "actor_name": "Alicia Cozine",
          "created_at": "2022-04-28T19:56:28",
          "type": "closed"
        },
        {
          "actor_name": "Alicia Cozine",
          "created_at": "2022-04-28T19:56:28",
          "type": "head_ref_deleted"
        }
      ],
      "pr_html_url": "https://github.com/pulibrary/princeton_ansible/pull/3000",
      "action": "pull_request_closed"
    },
    {
      "created_at": "2022-04-28T20:02:48",
      "updated_at": "2022-04-28T20:02:48",
      "html_url": "https://github.com/pulibrary/princeton_ansible/pull/3004",
      "number": 3004,
      "pull_request_html_url": "https://github.com/pulibrary/princeton_ansible/pull/3004",
      "repository_html_url": "https://github.com/pulibrary/princeton_ansible",
      "repository_name": "princeton_ansible",
      "state": "open",
      "title": "Add AWS keys to PDC Describe so it can read from S3",
      "user_name": "Bess Sadler",
      "comments": [],
      "events": [],
      "pr_html_url": "https://github.com/pulibrary/princeton_ansible/pull/3004",
      "action": "pull_request_open"
    },
    {
      "created_at": "2022-04-27T13:54:21",
      "updated_at": "2022-04-27T13:54:21",
      "html_url": "https://github.com/pulibrary/princeton_ansible/pull/2993",
      "number": 2993,
      "pull_request_html_url": "https://github.com/pulibrary/princeton_ansible/pull/2993",
      "repository_html_url": "https://github.com/pulibrary/princeton_ansible",
      "repository_name": "princeton_ansible",
      "state": "open",
      "title": "move special collections to new database",
      "user_name": "Francis Kayiwa",
      "comments": [
        {
          "user_name": "Alicia Cozine",
          "updated_at": "2022-04-28T20:18:46",
          "html_url": "https://github.com/pulibrary/princeton_ansible/pull/2993#issuecomment-1112617521",
          "body": "Related to #2737."
        }
      ],
      "events": [],
      "pr_html_url": "https://github.com/pulibrary/princeton_ansible/pull/2993",
      "action": "pull_request_open"
    },
    {
      "created_at": "2022-04-28T12:16:39",
      "updated_at": "2022-04-28T12:16:39",
      "html_url": "https://github.com/pulibrary/princeton_ansible/pull/2998",
      "number": 2998,
      "pull_request_html_url": "https://github.com/pulibrary/princeton_ansible/pull/2998",
      "repository_html_url": "https://github.com/pulibrary/princeton_ansible",
      "repository_name": "princeton_ansible",
      "state": "open",
      "title": "i2720 migrate pas",
      "user_name": "Francis Kayiwa",
      "comments": [
        {
          "user_name": "Alicia Cozine",
          "updated_at": "2022-04-28T20:19:40",
          "html_url": "https://github.com/pulibrary/princeton_ansible/pull/2998#issuecomment-1112618191",
          "body": "Related to #2737."
        }
      ],
      "events": [
        {
          "actor_name": "Francis Kayiwa",
          "created_at": "2022-04-28T13:46:41",
          "type": "review_requested"
        }
      ],
      "pr_html_url": "https://github.com/pulibrary/princeton_ansible/pull/2998",
      "action": "pull_request_open"
    },
    {
      "created_at": "2022-04-08T21:23:58",
      "updated_at": "2022-04-08T21:23:58",
      "html_url": "https://github.com/pulibrary/princeton_ansible/issues/2949",
      "number": 2949,
      "pull_request_html_url": null,
      "repository_html_url": "https://github.com/pulibrary/princeton_ansible",
      "repository_name": "princeton_ansible",
      "state": "closed",
      "title": "Update postgresql task FQCNs to use community.postgresql",
      "user_name": "Alicia Cozine",
      "comments": [],
      "events": [
        {
          "actor_name": "Alicia Cozine",
          "created_at": "2022-04-28T20:21:17",
          "type": "closed"
        }
      ],
      "pr_html_url": null,
      "action": "closed"
    },
    {
      "created_at": "2022-04-27T13:36:30",
      "updated_at": "2022-04-27T13:36:30",
      "html_url": "https://github.com/pulibrary/princeton_ansible/pull/2992",
      "number": 2992,
      "pull_request_html_url": "https://github.com/pulibrary/princeton_ansible/pull/2992",
      "repository_html_url": "https://github.com/pulibrary/princeton_ansible",
      "repository_name": "princeton_ansible",
      "state": "closed",
      "title": "use the community.postgres FQCN",
      "user_name": "Francis Kayiwa",
      "comments": [],
      "events": [
        {
          "actor_name": "Alicia Cozine",
          "created_at": "2022-04-28T20:21:17",
          "type": "referenced"
        },
        {
          "actor_name": "Alicia Cozine",
          "created_at": "2022-04-28T20:21:17",
          "type": "merged"
        },
        {
          "actor_name": "Alicia Cozine",
          "created_at": "2022-04-28T20:21:18",
          "type": "closed"
        },
        {
          "actor_name": "Alicia Cozine",
          "created_at": "2022-04-28T20:21:18",
          "type": "head_ref_deleted"
        }
      ],
      "pr_html_url": "https://github.com/pulibrary/princeton_ansible/pull/2992",
      "action": "pull_request_closed"
    },
    {
      "created_at": "2022-02-16T15:40:03",
      "updated_at": "2022-02-16T15:40:03",
      "html_url": "https://github.com/pulibrary/princeton_ansible/pull/2764",
      "number": 2764,
      "pull_request_html_url": "https://github.com/pulibrary/princeton_ansible/pull/2764",
      "repository_html_url": "https://github.com/pulibrary/princeton_ansible",
      "repository_name": "princeton_ansible",
      "state": "closed",
      "title": "i2720 migrate mariadb staging",
      "user_name": "Francis Kayiwa",
      "comments": [],
      "events": [
        {
          "actor_name": "Alicia Cozine",
          "created_at": "2022-04-28T20:22:42",
          "type": "head_ref_deleted"
        }
      ],
      "pr_html_url": "https://github.com/pulibrary/princeton_ansible/pull/2764",
      "action": "pull_request_closed"
    },
    {
      "created_at": "2022-04-28T17:28:52",
      "updated_at": "2022-04-28T17:28:52",
      "html_url": "https://github.com/pulibrary/princeton_ansible/pull/3002",
      "number": 3002,
      "pull_request_html_url": "https://github.com/pulibrary/princeton_ansible/pull/3002",
      "repository_html_url": "https://github.com/pulibrary/princeton_ansible",
      "repository_name": "princeton_ansible",
      "state": "closed",
      "title": "adds renewed pulfalight-staging TLS certs",
      "user_name": "Francis Kayiwa",
      "comments": [],
      "events": [
        {
          "actor_name": "Francis Kayiwa",
          "created_at": "2022-04-28T17:30:14",
          "type": "head_ref_force_pushed"
        },
        {
          "actor_name": "Alicia Cozine",
          "created_at": "2022-04-28T20:24:33",
          "type": "referenced"
        },
        {
          "actor_name": "Alicia Cozine",
          "created_at": "2022-04-28T20:24:33",
          "type": "merged"
        },
        {
          "actor_name": "Alicia Cozine",
          "created_at": "2022-04-28T20:24:33",
          "type": "closed"
        },
        {
          "actor_name": "Alicia Cozine",
          "created_at": "2022-04-28T20:24:34",
          "type": "head_ref_deleted"
        }
      ],
      "pr_html_url": "https://github.com/pulibrary/princeton_ansible/pull/3002",
      "action": "pull_request_closed"
    },
    {
      "created_at": "2022-04-28T17:00:08",
      "updated_at": "2022-04-28T17:00:08",
      "html_url": "https://github.com/pulibrary/princeton_ansible/pull/3001",
      "number": 3001,
      "pull_request_html_url": "https://github.com/pulibrary/princeton_ansible/pull/3001",
      "repository_html_url": "https://github.com/pulibrary/princeton_ansible",
      "repository_name": "princeton_ansible",
      "state": "closed",
      "title": "Update datadog tls domain for bibdata",
      "user_name": "Jane Sandberg",
      "comments": [],
      "events": [
        {
          "actor_name": "Alicia Cozine",
          "created_at": "2022-04-28T20:46:28",
          "type": "referenced"
        },
        {
          "actor_name": "Alicia Cozine",
          "created_at": "2022-04-28T20:46:28",
          "type": "merged"
        },
        {
          "actor_name": "Alicia Cozine",
          "created_at": "2022-04-28T20:46:28",
          "type": "closed"
        },
        {
          "actor_name": "Alicia Cozine",
          "created_at": "2022-04-28T20:46:29",
          "type": "head_ref_deleted"
        }
      ],
      "pr_html_url": "https://github.com/pulibrary/princeton_ansible/pull/3001",
      "action": "pull_request_closed"
    }
  ],
  "pul-the-hard-way": [
    {
      "created_at": "2022-03-23T18:20:02",
      "updated_at": "2022-03-23T18:20:02",
      "html_url": "https://github.com/pulibrary/pul-the-hard-way/pull/108",
      "number": 108,
      "pull_request_html_url": "https://github.com/pulibrary/pul-the-hard-way/pull/108",
      "repository_html_url": "https://github.com/pulibrary/pul-the-hard-way",
      "repository_name": "pul-the-hard-way",
      "state": "closed",
      "title": "Add VPN IP resolution documentation/tool",
      "user_name": "Trey Pendragon",
      "comments": [],
      "events": [
        {
          "actor_name": null,
          "created_at": "2022-04-28T15:51:50",
          "type": "referenced"
        },
        {
          "actor_name": null,
          "created_at": "2022-04-28T15:51:50",
          "type": "merged"
        },
        {
          "actor_name": null,
          "created_at": "2022-04-28T15:51:50",
          "type": "closed"
        },
        {
          "actor_name": null,
          "created_at": "2022-04-28T15:51:51",
          "type": "head_ref_deleted"
        }
      ],
      "pr_html_url": "https://github.com/pulibrary/pul-the-hard-way/pull/108",
      "action": "pull_request_closed"
    }
  ],
  "pul_solr": [
    {
      "created_at": "2022-04-27T18:16:30",
      "updated_at": "2022-04-27T18:16:30",
      "html_url": "https://github.com/pulibrary/pul_solr/pull/332",
      "number": 332,
      "pull_request_html_url": "https://github.com/pulibrary/pul_solr/pull/332",
      "repository_html_url": "https://github.com/pulibrary/pul_solr",
      "repository_name": "pul_solr",
      "state": "closed",
      "title": "[pulfalight] Boost component results whose collection title matches query",
      "user_name": "hackartisan",
      "comments": [],
      "events": [
        {
          "actor_name": null,
          "created_at": "2022-04-28T15:43:01",
          "type": "ready_for_review"
        },
        {
          "actor_name": "Trey Pendragon",
          "created_at": "2022-04-28T15:43:32",
          "type": "referenced"
        },
        {
          "actor_name": "Trey Pendragon",
          "created_at": "2022-04-28T15:43:32",
          "type": "merged"
        },
        {
          "actor_name": "Trey Pendragon",
          "created_at": "2022-04-28T15:43:32",
          "type": "closed"
        },
        {
          "actor_name": "Trey Pendragon",
          "created_at": "2022-04-28T15:43:33",
          "type": "head_ref_deleted"
        }
      ],
      "pr_html_url": "https://github.com/pulibrary/pul_solr/pull/332",
      "action": "pull_request_closed"
    }
  ],
  "pulbot": [
    {
      "created_at": "2022-04-28T14:07:35",
      "updated_at": "2022-04-28T14:07:35",
      "html_url": "https://github.com/pulibrary/pulbot/pull/107",
      "number": 107,
      "pull_request_html_url": "https://github.com/pulibrary/pulbot/pull/107",
      "repository_html_url": "https://github.com/pulibrary/pulbot",
      "repository_name": "pulbot",
      "state": "closed",
      "title": "Offboard Xander",
      "user_name": "hackartisan",
      "comments": [],
      "events": [
        {
          "actor_name": "Eliot Jordan",
          "created_at": "2022-04-28T15:05:55",
          "type": "referenced"
        },
        {
          "actor_name": "Eliot Jordan",
          "created_at": "2022-04-28T15:05:55",
          "type": "merged"
        },
        {
          "actor_name": "Eliot Jordan",
          "created_at": "2022-04-28T15:05:55",
          "type": "closed"
        },
        {
          "actor_name": "Eliot Jordan",
          "created_at": "2022-04-28T15:05:56",
          "type": "head_ref_deleted"
        }
      ],
      "pr_html_url": "https://github.com/pulibrary/pulbot/pull/107",
      "action": "pull_request_closed"
    }
  ],
  "pulfalight": [
    {
      "created_at": "2021-03-12T21:24:39",
      "updated_at": "2021-03-12T21:24:39",
      "html_url": "https://github.com/pulibrary/pulfalight/issues/755",
      "number": 755,
      "pull_request_html_url": null,
      "repository_html_url": "https://github.com/pulibrary/pulfalight",
      "repository_name": "pulfalight",
      "state": "closed",
      "title": "Oversize folders should create a transaction in aeon per folder if there's multiple folders in a component",
      "user_name": "Trey Pendragon",
      "comments": [],
      "events": [
        {
          "actor_name": "Trey Pendragon",
          "created_at": "2022-04-28T14:02:26",
          "type": "closed"
        }
      ],
      "pr_html_url": null,
      "action": "closed"
    },
    {
      "created_at": "2022-04-27T21:42:09",
      "updated_at": "2022-04-27T21:42:09",
      "html_url": "https://github.com/pulibrary/pulfalight/pull/1040",
      "number": 1040,
      "pull_request_html_url": "https://github.com/pulibrary/pulfalight/pull/1040",
      "repository_html_url": "https://github.com/pulibrary/pulfalight",
      "repository_name": "pulfalight",
      "state": "closed",
      "title": "Add oversize folders as top containers for requesting.",
      "user_name": "Trey Pendragon",
      "comments": [],
      "events": [
        {
          "actor_name": "Trey Pendragon",
          "created_at": "2022-04-28T14:02:26",
          "type": "referenced"
        },
        {
          "actor_name": "Trey Pendragon",
          "created_at": "2022-04-28T14:02:26",
          "type": "merged"
        },
        {
          "actor_name": "Trey Pendragon",
          "created_at": "2022-04-28T14:02:27",
          "type": "closed"
        },
        {
          "actor_name": "Trey Pendragon",
          "created_at": "2022-04-28T14:02:27",
          "type": "head_ref_deleted"
        }
      ],
      "pr_html_url": "https://github.com/pulibrary/pulfalight/pull/1040",
      "action": "pull_request_closed"
    },
    {
      "created_at": "2022-04-27T20:23:40",
      "updated_at": "2022-04-27T20:23:40",
      "html_url": "https://github.com/pulibrary/pulfalight/issues/1038",
      "number": 1038,
      "pull_request_html_url": null,
      "repository_html_url": "https://github.com/pulibrary/pulfalight",
      "repository_name": "pulfalight",
      "state": "closed",
      "title": "Bioghist notes are gone from components",
      "user_name": "Trey Pendragon",
      "comments": [],
      "events": [
        {
          "actor_name": "Trey Pendragon",
          "created_at": "2022-04-28T14:02:40",
          "type": "closed"
        }
      ],
      "pr_html_url": null,
      "action": "closed"
    },
    {
      "created_at": "2022-04-27T21:00:20",
      "updated_at": "2022-04-27T21:00:20",
      "html_url": "https://github.com/pulibrary/pulfalight/pull/1039",
      "number": 1039,
      "pull_request_html_url": "https://github.com/pulibrary/pulfalight/pull/1039",
      "repository_html_url": "https://github.com/pulibrary/pulfalight",
      "repository_name": "pulfalight",
      "state": "closed",
      "title": "Add bioghist back to components.",
      "user_name": "Trey Pendragon",
      "comments": [],
      "events": [
        {
          "actor_name": "Trey Pendragon",
          "created_at": "2022-04-28T14:02:40",
          "type": "referenced"
        },
        {
          "actor_name": "Trey Pendragon",
          "created_at": "2022-04-28T14:02:40",
          "type": "merged"
        },
        {
          "actor_name": "Trey Pendragon",
          "created_at": "2022-04-28T14:02:41",
          "type": "closed"
        },
        {
          "actor_name": "Trey Pendragon",
          "created_at": "2022-04-28T14:02:41",
          "type": "head_ref_deleted"
        }
      ],
      "pr_html_url": "https://github.com/pulibrary/pulfalight/pull/1039",
      "action": "pull_request_closed"
    },
    {
      "created_at": "2021-04-12T17:59:00",
      "updated_at": "2021-04-12T17:59:00",
      "html_url": "https://github.com/pulibrary/pulfalight/issues/799",
      "number": 799,
      "pull_request_html_url": null,
      "repository_html_url": "https://github.com/pulibrary/pulfalight",
      "repository_name": "pulfalight",
      "state": "open",
      "title": "XML Display for Components are broken",
      "user_name": "Trey Pendragon",
      "comments": [],
      "events": [
        {
          "actor_name": "Eliot Jordan",
          "created_at": "2022-04-28T14:44:55",
          "type": "assigned"
        }
      ],
      "pr_html_url": null,
      "action": "updated"
    },
    {
      "created_at": "2022-04-27T18:16:46",
      "updated_at": "2022-04-27T18:16:46",
      "html_url": "https://github.com/pulibrary/pulfalight/pull/1036",
      "number": 1036,
      "pull_request_html_url": "https://github.com/pulibrary/pulfalight/pull/1036",
      "repository_html_url": "https://github.com/pulibrary/pulfalight",
      "repository_name": "pulfalight",
      "state": "closed",
      "title": "Boost component results whose collection title matches query",
      "user_name": "hackartisan",
      "comments": [],
      "events": [
        {
          "actor_name": null,
          "created_at": "2022-04-28T15:42:56",
          "type": "ready_for_review"
        },
        {
          "actor_name": "Trey Pendragon",
          "created_at": "2022-04-28T15:44:19",
          "type": "referenced"
        },
        {
          "actor_name": "Trey Pendragon",
          "created_at": "2022-04-28T15:44:19",
          "type": "merged"
        },
        {
          "actor_name": "Trey Pendragon",
          "created_at": "2022-04-28T15:44:20",
          "type": "closed"
        },
        {
          "actor_name": "Trey Pendragon",
          "created_at": "2022-04-28T15:44:21",
          "type": "head_ref_deleted"
        }
      ],
      "pr_html_url": "https://github.com/pulibrary/pulfalight/pull/1036",
      "action": "pull_request_closed"
    },
    {
      "created_at": "2022-04-28T14:38:30",
      "updated_at": "2022-04-28T14:38:30",
      "html_url": "https://github.com/pulibrary/pulfalight/issues/1041",
      "number": 1041,
      "pull_request_html_url": null,
      "repository_html_url": "https://github.com/pulibrary/pulfalight",
      "repository_name": "pulfalight",
      "state": "open",
      "title": "Search Results showing at the collection level with a match. ",
      "user_name": "Christa Cleeton",
      "comments": [
        {
          "user_name": "Shaun Ellis",
          "updated_at": "2022-04-28T14:53:38",
          "html_url": "https://github.com/pulibrary/pulfalight/issues/1041#issuecomment-1112307231",
          "body": "@ccleeton that search groups results by collection. Unfortunately, there is no keyword highlighting in the Grouped Results. If you click on All Results, you will see that it's matching on \"Kenneth\". If you want to search for an exact match for \"Kenneth Kuan-Sheng Chen\", you need to put the full name in quotes."
        },
        {
          "user_name": "Christa Cleeton",
          "updated_at": "2022-04-28T14:56:50",
          "html_url": "https://github.com/pulibrary/pulfalight/issues/1041#issuecomment-1112310677",
          "body": "Ahhh lets keep this open because it is not intuitive or clear"
        },
        {
          "user_name": "Christa Cleeton",
          "updated_at": "2022-04-28T17:39:23",
          "html_url": "https://github.com/pulibrary/pulfalight/issues/1041#issuecomment-1112487906",
          "body": "@phoebeno also notes \"I always get CFR when I am typing in a name that does not exist anywhere else\""
        }
      ],
      "events": [
        {
          "actor_name": "Christa Cleeton",
          "created_at": "2022-04-28T14:38:30",
          "type": "labeled"
        },
        {
          "actor_name": "Christa Cleeton",
          "created_at": "2022-04-28T14:53:39",
          "type": "mentioned"
        },
        {
          "actor_name": "Christa Cleeton",
          "created_at": "2022-04-28T14:53:39",
          "type": "subscribed"
        },
        {
          "actor_name": null,
          "created_at": "2022-04-28T17:39:23",
          "type": "mentioned"
        },
        {
          "actor_name": null,
          "created_at": "2022-04-28T17:39:23",
          "type": "subscribed"
        }
      ],
      "pr_html_url": null,
      "action": "created"
    },
    {
      "created_at": "2022-02-15T16:59:57",
      "updated_at": "2022-02-15T16:59:57",
      "html_url": "https://github.com/pulibrary/pulfalight/issues/982",
      "number": 982,
      "pull_request_html_url": null,
      "repository_html_url": "https://github.com/pulibrary/pulfalight",
      "repository_name": "pulfalight",
      "state": "open",
      "title": "Search results for James Baker",
      "user_name": "Christa Cleeton",
      "comments": [
        {
          "user_name": "hackartisan",
          "updated_at": "2022-04-28T15:50:24",
          "html_url": "https://github.com/pulibrary/pulfalight/issues/982#issuecomment-1112372572",
          "body": "reopening until it's deployed and the full reindex is run."
        }
      ],
      "events": [
        {
          "actor_name": "Trey Pendragon",
          "created_at": "2022-04-28T15:43:33",
          "type": "referenced"
        },
        {
          "actor_name": "Trey Pendragon",
          "created_at": "2022-04-28T15:44:19",
          "type": "closed"
        },
        {
          "actor_name": null,
          "created_at": "2022-04-28T17:59:37",
          "type": "reopened"
        }
      ],
      "pr_html_url": null,
      "action": "updated"
    },
    {
      "created_at": "2021-11-05T19:53:12",
      "updated_at": "2021-11-05T19:53:12",
      "html_url": "https://github.com/pulibrary/pulfalight/issues/926",
      "number": 926,
      "pull_request_html_url": null,
      "repository_html_url": "https://github.com/pulibrary/pulfalight",
      "repository_name": "pulfalight",
      "state": "open",
      "title": "Resources updated in Pulfalight should update their metadata in Figgy automatically",
      "user_name": "Trey Pendragon",
      "comments": [],
      "events": [],
      "pr_html_url": null,
      "action": "updated"
    },
    {
      "created_at": "2022-04-27T14:25:58",
      "updated_at": "2022-04-27T14:25:58",
      "html_url": "https://github.com/pulibrary/pulfalight/issues/1034",
      "number": 1034,
      "pull_request_html_url": null,
      "repository_html_url": "https://github.com/pulibrary/pulfalight",
      "repository_name": "pulfalight",
      "state": "open",
      "title": "Document what to do if you can't access the aspace api",
      "user_name": "hackartisan",
      "comments": [],
      "events": [
        {
          "actor_name": null,
          "created_at": "2022-04-28T18:04:02",
          "type": "labeled"
        }
      ],
      "pr_html_url": null,
      "action": "updated"
    },
    {
      "created_at": "2022-04-28T15:16:31",
      "updated_at": "2022-04-28T15:16:31",
      "html_url": "https://github.com/pulibrary/pulfalight/issues/1042",
      "number": 1042,
      "pull_request_html_url": null,
      "repository_html_url": "https://github.com/pulibrary/pulfalight",
      "repository_name": "pulfalight",
      "state": "open",
      "title": "internal only resources can't index because there's no id at the given path",
      "user_name": "hackartisan",
      "comments": [],
      "events": [
        {
          "actor_name": null,
          "created_at": "2022-04-28T15:16:57",
          "type": "renamed"
        },
        {
          "actor_name": null,
          "created_at": "2022-04-28T15:18:23",
          "type": "labeled"
        },
        {
          "actor_name": null,
          "created_at": "2022-04-28T18:32:31",
          "type": "assigned"
        },
        {
          "actor_name": null,
          "created_at": "2022-04-28T18:37:49",
          "type": "referenced"
        }
      ],
      "pr_html_url": null,
      "action": "created"
    },
    {
      "created_at": "2022-01-18T19:15:09",
      "updated_at": "2022-01-18T19:15:09",
      "html_url": "https://github.com/pulibrary/pulfalight/issues/962",
      "number": 962,
      "pull_request_html_url": null,
      "repository_html_url": "https://github.com/pulibrary/pulfalight",
      "repository_name": "pulfalight",
      "state": "open",
      "title": "Add text welcoming feedback on items to the home page of the site.",
      "user_name": "Trey Pendragon",
      "comments": [
        {
          "user_name": "hackartisan",
          "updated_at": "2022-04-28T14:56:42",
          "html_url": "https://github.com/pulibrary/pulfalight/issues/962#issuecomment-1112310525",
          "body": "We need to figure out where to put this."
        },
        {
          "user_name": "Christa Cleeton",
          "updated_at": "2022-04-28T15:06:33",
          "html_url": "https://github.com/pulibrary/pulfalight/issues/962#issuecomment-1112324081",
          "body": "If I am reading/remembering it needs to be on the main landing page? Not that I like this idea but maybe a smaller banner? "
        },
        {
          "user_name": "hackartisan",
          "updated_at": "2022-04-28T15:59:33",
          "html_url": "https://github.com/pulibrary/pulfalight/issues/962#issuecomment-1112382997",
          "body": "Maybe a 3rd column after hours and \"request materials\"? we could move the create account button below the text saying you'll need to create an account."
        },
        {
          "user_name": "Christa Cleeton",
          "updated_at": "2022-04-28T16:02:32",
          "html_url": "https://github.com/pulibrary/pulfalight/issues/962#issuecomment-1112385987",
          "body": "I don't hate that idea. :)\r\n"
        }
      ],
      "events": [
        {
          "actor_name": null,
          "created_at": "2022-04-28T18:40:17",
          "type": "assigned"
        },
        {
          "actor_name": null,
          "created_at": "2022-04-28T19:03:18",
          "type": "referenced"
        },
        {
          "actor_name": null,
          "created_at": "2022-04-28T19:05:21",
          "type": "referenced"
        }
      ],
      "pr_html_url": null,
      "action": "updated"
    },
    {
      "created_at": "2022-04-28T19:05:41",
      "updated_at": "2022-04-28T19:05:41",
      "html_url": "https://github.com/pulibrary/pulfalight/pull/1044",
      "number": 1044,
      "pull_request_html_url": "https://github.com/pulibrary/pulfalight/pull/1044",
      "repository_html_url": "https://github.com/pulibrary/pulfalight",
      "repository_name": "pulfalight",
      "state": "open",
      "title": "Add feedback welcome text to home page",
      "user_name": "hackartisan",
      "comments": [],
      "events": [],
      "pr_html_url": "https://github.com/pulibrary/pulfalight/pull/1044",
      "action": "pull_request_open"
    },
    {
      "created_at": "2022-04-28T18:38:04",
      "updated_at": "2022-04-28T18:38:04",
      "html_url": "https://github.com/pulibrary/pulfalight/pull/1043",
      "number": 1043,
      "pull_request_html_url": "https://github.com/pulibrary/pulfalight/pull/1043",
      "repository_html_url": "https://github.com/pulibrary/pulfalight",
      "repository_name": "pulfalight",
      "state": "open",
      "title": "Use a different field to pull id",
      "user_name": "hackartisan",
      "comments": [],
      "events": [],
      "pr_html_url": "https://github.com/pulibrary/pulfalight/pull/1043",
      "action": "pull_request_open"
    },
    {
      "created_at": "2022-04-26T17:03:25",
      "updated_at": "2022-04-26T17:03:25",
      "html_url": "https://github.com/pulibrary/pulfalight/pull/1033",
      "number": 1033,
      "pull_request_html_url": "https://github.com/pulibrary/pulfalight/pull/1033",
      "repository_html_url": "https://github.com/pulibrary/pulfalight",
      "repository_name": "pulfalight",
      "state": "open",
      "title": "Adds Ask Us Button to homepage",
      "user_name": "Shaun Ellis",
      "comments": [],
      "events": [],
      "pr_html_url": "https://github.com/pulibrary/pulfalight/pull/1033",
      "action": "pull_request_open"
    },
    {
      "created_at": "2022-04-27T16:08:47",
      "updated_at": "2022-04-27T16:08:47",
      "html_url": "https://github.com/pulibrary/pulfalight/pull/1035",
      "number": 1035,
      "pull_request_html_url": "https://github.com/pulibrary/pulfalight/pull/1035",
      "repository_html_url": "https://github.com/pulibrary/pulfalight",
      "repository_name": "pulfalight",
      "state": "open",
      "title": "Embed viewers and download links from figgy graphql endpoint",
      "user_name": "hackartisan",
      "comments": [],
      "events": [
        {
          "actor_name": null,
          "created_at": "2022-04-28T15:21:47",
          "type": "head_ref_force_pushed"
        },
        {
          "actor_name": null,
          "created_at": "2022-04-28T15:22:11",
          "type": "deployed"
        },
        {
          "actor_name": null,
          "created_at": "2022-04-28T17:53:27",
          "type": "deployed"
        },
        {
          "actor_name": null,
          "created_at": "2022-04-28T21:57:37",
          "type": "deployed"
        },
        {
          "actor_name": null,
          "created_at": "2022-04-28T22:06:50",
          "type": "deployed"
        }
      ],
      "pr_html_url": "https://github.com/pulibrary/pulfalight/pull/1035",
      "action": "pull_request_open"
    }
  ],
  "pulmap": [
    {
      "created_at": "2022-04-28T21:10:16",
      "updated_at": "2022-04-28T21:10:16",
      "html_url": "https://github.com/pulibrary/pulmap/pull/1084",
      "number": 1084,
      "pull_request_html_url": "https://github.com/pulibrary/pulmap/pull/1084",
      "repository_html_url": "https://github.com/pulibrary/pulmap",
      "repository_name": "pulmap",
      "state": "open",
      "title": "Bump async from 2.6.3 to 2.6.4",
      "user_name": "dependabot[bot]",
      "comments": [],
      "events": [
        {
          "actor_name": null,
          "created_at": "2022-04-28T21:10:17",
          "type": "labeled"
        },
        {
          "actor_name": null,
          "created_at": "2022-04-28T21:10:17",
          "type": "labeled"
        }
      ],
      "pr_html_url": "https://github.com/pulibrary/pulmap/pull/1084",
      "action": "pull_request_open"
    }
  ],
  "rdss-catchall": [
    {
      "created_at": "2022-04-20T18:55:18",
      "updated_at": "2022-04-20T18:55:18",
      "html_url": "https://github.com/pulibrary/rdss-catchall/issues/51",
      "number": 51,
      "pull_request_html_url": null,
      "repository_html_url": "https://github.com/pulibrary/rdss-catchall",
      "repository_name": "rdss-catchall",
      "state": "open",
      "title": "Import 30 dissertations",
      "user_name": "Bess Sadler",
      "comments": [],
      "events": [
        {
          "actor_name": "Bess Sadler",
          "created_at": "2022-04-28T19:59:53",
          "type": "assigned"
        }
      ],
      "pr_html_url": null,
      "action": "updated"
    }
  ],
  "uptime": [
    {
      "created_at": "2022-04-28T02:18:50",
      "updated_at": "2022-04-28T02:18:50",
      "html_url": "https://github.com/pulibrary/uptime/issues/405",
      "number": 405,
      "pull_request_html_url": null,
      "repository_html_url": "https://github.com/pulibrary/uptime",
      "repository_name": "uptime",
      "state": "closed",
      "title": "🛑 Library Catalog is down",
      "user_name": "Francis Kayiwa",
      "comments": [
        {
          "user_name": "Francis Kayiwa",
          "updated_at": "2022-04-28T03:18:42",
          "html_url": "https://github.com/pulibrary/uptime/issues/405#issuecomment-1111698641",
          "body": "**Resolved:** Library Catalog is back up in [`973ff8b`](https://github.com/pulibrary/uptime/commit/973ff8b75eb2023eed5dbe4e3bf5421be486af1e\n)."
        }
      ],
      "events": [
        {
          "actor_name": "Francis Kayiwa",
          "created_at": "2022-04-28T02:18:50",
          "type": "labeled"
        },
        {
          "actor_name": "Francis Kayiwa",
          "created_at": "2022-04-28T02:18:50",
          "type": "labeled"
        },
        {
          "actor_name": "Francis Kayiwa",
          "created_at": "2022-04-28T02:18:51",
          "type": "locked"
        },
        {
          "actor_name": "Francis Kayiwa",
          "created_at": "2022-04-28T03:18:43",
          "type": "closed"
        }
      ],
      "pr_html_url": null,
      "action": "created"
    }
  ],
  "__meta__": {
    "issue_count": 59,
    "closed_count": 4,
    "created_count": 6,
    "pull_request_closed_count": 20,
    "pull_request_open_count": 15,
    "updated_count": 14,
    "today": "2022-04-28T22:00:05",
    "yesterday": "2022-04-27T22:00:05"
  }
}