{
  "alma-notices": [
    {
      "created_at": "2021-05-11T14:18:32",
      "updated_at": "2021-05-11T14:18:32",
      "html_url": "https://github.com/pulibrary/alma-notices/issues/27",
      "number": 27,
      "pull_request_html_url": null,
      "repository_html_url": "https://github.com/pulibrary/alma-notices",
      "repository_name": "alma-notices",
      "state": "closed",
      "title": "Ful Hold Shelf Request Slip Letter doesn't display barcode, location_name",
      "user_name": "regineheberlein",
      "comments": [],
      "events": [
        {
          "actor_name": null,
          "created_at": "2021-06-17T15:23:10",
          "type": "closed"
        }
      ],
      "pr_html_url": null,
      "action": "closed"
    }
  ],
  "alma_experimentation": [
    {
      "created_at": "2020-07-09T21:50:55",
      "updated_at": "2020-07-09T21:50:55",
      "html_url": "https://github.com/pulibrary/alma_experimentation/issues/22",
      "number": 22,
      "pull_request_html_url": null,
      "repository_html_url": "https://github.com/pulibrary/alma_experimentation",
      "repository_name": "alma_experimentation",
      "state": "closed",
      "title": "Review Electronic Resource Availability in Alma",
      "user_name": "Kevin Reiss",
      "comments": [],
      "events": [
        {
          "actor_name": null,
          "created_at": "2021-06-17T20:22:32",
          "type": "closed"
        }
      ],
      "pr_html_url": null,
      "action": "closed"
    },
    {
      "created_at": "2020-05-05T13:29:13",
      "updated_at": "2020-05-05T13:29:13",
      "html_url": "https://github.com/pulibrary/alma_experimentation/issues/2",
      "number": 2,
      "pull_request_html_url": null,
      "repository_html_url": "https://github.com/pulibrary/alma_experimentation",
      "repository_name": "alma_experimentation",
      "state": "closed",
      "title": "Document Alma record structure",
      "user_name": "mzelesky",
      "comments": [],
      "events": [
        {
          "actor_name": null,
          "created_at": "2021-06-17T20:22:39",
          "type": "closed"
        }
      ],
      "pr_html_url": null,
      "action": "closed"
    },
    {
      "created_at": "2020-07-09T15:19:09",
      "updated_at": "2020-07-09T15:19:09",
      "html_url": "https://github.com/pulibrary/alma_experimentation/issues/11",
      "number": 11,
      "pull_request_html_url": null,
      "repository_html_url": "https://github.com/pulibrary/alma_experimentation",
      "repository_name": "alma_experimentation",
      "state": "closed",
      "title": "Review and Document Staff User Profiles",
      "user_name": "Kevin Reiss",
      "comments": [],
      "events": [
        {
          "actor_name": null,
          "created_at": "2021-06-17T20:23:06",
          "type": "closed"
        }
      ],
      "pr_html_url": null,
      "action": "closed"
    },
    {
      "created_at": "2020-07-16T15:42:48",
      "updated_at": "2020-07-16T15:42:48",
      "html_url": "https://github.com/pulibrary/alma_experimentation/issues/27",
      "number": 27,
      "pull_request_html_url": null,
      "repository_html_url": "https://github.com/pulibrary/alma_experimentation",
      "repository_name": "alma_experimentation",
      "state": "closed",
      "title": "ILLiad configuration",
      "user_name": "mzelesky",
      "comments": [],
      "events": [
        {
          "actor_name": null,
          "created_at": "2021-06-17T20:23:14",
          "type": "closed"
        }
      ],
      "pr_html_url": null,
      "action": "closed"
    },
    {
      "created_at": "2020-07-14T21:31:45",
      "updated_at": "2020-07-14T21:31:45",
      "html_url": "https://github.com/pulibrary/alma_experimentation/issues/26",
      "number": 26,
      "pull_request_html_url": null,
      "repository_html_url": "https://github.com/pulibrary/alma_experimentation",
      "repository_name": "alma_experimentation",
      "state": "closed",
      "title": "Normalization rules",
      "user_name": "Peter Green",
      "comments": [],
      "events": [
        {
          "actor_name": null,
          "created_at": "2021-06-17T20:23:49",
          "type": "closed"
        }
      ],
      "pr_html_url": null,
      "action": "closed"
    }
  ],
  "bibdata": [
    {
      "created_at": "2020-10-13T14:11:04",
      "updated_at": "2020-10-13T14:11:04",
      "html_url": "https://github.com/pulibrary/bibdata/issues/855",
      "number": 855,
      "pull_request_html_url": null,
      "repository_html_url": "https://github.com/pulibrary/bibdata",
      "repository_name": "bibdata",
      "state": "closed",
      "title": "Clean up dump files on sftp server",
      "user_name": "hackartisan",
      "comments": [],
      "events": [
        {
          "actor_name": "Christina Chortaria",
          "created_at": "2021-06-16T23:03:15",
          "type": "closed"
        }
      ],
      "pr_html_url": null,
      "action": "closed"
    },
    {
      "created_at": "2021-06-16T19:23:56",
      "updated_at": "2021-06-16T19:23:56",
      "html_url": "https://github.com/pulibrary/bibdata/pull/1427",
      "number": 1427,
      "pull_request_html_url": "https://github.com/pulibrary/bibdata/pull/1427",
      "repository_html_url": "https://github.com/pulibrary/bibdata",
      "repository_name": "bibdata",
      "state": "closed",
      "title": "Timeout values for deletes",
      "user_name": "Hector Correa",
      "comments": [
        {
          "user_name": "James R. Griffin III",
          "updated_at": "2021-06-17T13:14:55",
          "html_url": "https://github.com/pulibrary/bibdata/pull/1427#issuecomment-863229230",
          "body": "I was not aware of these options, but for reference, please see https://lostisland.github.io/faraday/usage/customize"
        }
      ],
      "events": [
        {
          "actor_name": "James R. Griffin III",
          "created_at": "2021-06-17T13:14:59",
          "type": "referenced"
        },
        {
          "actor_name": "James R. Griffin III",
          "created_at": "2021-06-17T13:14:59",
          "type": "merged"
        },
        {
          "actor_name": "James R. Griffin III",
          "created_at": "2021-06-17T13:14:59",
          "type": "closed"
        },
        {
          "actor_name": "James R. Griffin III",
          "created_at": "2021-06-17T13:15:00",
          "type": "head_ref_deleted"
        }
      ],
      "pr_html_url": "https://github.com/pulibrary/bibdata/pull/1427",
      "action": "pull_request_closed"
    },
    {
      "created_at": "2021-06-16T22:59:04",
      "updated_at": "2021-06-16T22:59:04",
      "html_url": "https://github.com/pulibrary/bibdata/pull/1428",
      "number": 1428,
      "pull_request_html_url": "https://github.com/pulibrary/bibdata/pull/1428",
      "repository_html_url": "https://github.com/pulibrary/bibdata",
      "repository_name": "bibdata",
      "state": "closed",
      "title": "1412 availability.json holdings item level",
      "user_name": "Christina Chortaria",
      "comments": [],
      "events": [
        {
          "actor_name": "Christina Chortaria",
          "created_at": "2021-06-17T13:20:09",
          "type": "referenced"
        },
        {
          "actor_name": "Christina Chortaria",
          "created_at": "2021-06-17T13:20:09",
          "type": "merged"
        },
        {
          "actor_name": "Christina Chortaria",
          "created_at": "2021-06-17T13:20:09",
          "type": "closed"
        },
        {
          "actor_name": "Christina Chortaria",
          "created_at": "2021-06-17T13:20:10",
          "type": "head_ref_deleted"
        }
      ],
      "pr_html_url": "https://github.com/pulibrary/bibdata/pull/1428",
      "action": "pull_request_closed"
    },
    {
      "created_at": "2021-06-10T19:38:05",
      "updated_at": "2021-06-10T19:38:05",
      "html_url": "https://github.com/pulibrary/bibdata/issues/1412",
      "number": 1412,
      "pull_request_html_url": null,
      "repository_html_url": "https://github.com/pulibrary/bibdata",
      "repository_name": "bibdata",
      "state": "closed",
      "title": "Update the label in the availability.json in the item level",
      "user_name": "Christina Chortaria",
      "comments": [
        {
          "user_name": "Christina Chortaria",
          "updated_at": "2021-06-17T13:51:16",
          "html_url": "https://github.com/pulibrary/bibdata/issues/1412#issuecomment-863257311",
          "body": "closed by #1428 "
        }
      ],
      "events": [
        {
          "actor_name": "Christina Chortaria",
          "created_at": "2021-06-16T23:00:23",
          "type": "labeled"
        },
        {
          "actor_name": "Christina Chortaria",
          "created_at": "2021-06-17T13:51:16",
          "type": "closed"
        }
      ],
      "pr_html_url": null,
      "action": "closed"
    },
    {
      "created_at": "2021-06-15T19:55:58",
      "updated_at": "2021-06-15T19:55:58",
      "html_url": "https://github.com/pulibrary/bibdata/issues/1422",
      "number": 1422,
      "pull_request_html_url": null,
      "repository_html_url": "https://github.com/pulibrary/bibdata",
      "repository_name": "bibdata",
      "state": "open",
      "title": "Add a rake task to create an event-dump_file for local development",
      "user_name": "Christina Chortaria",
      "comments": [],
      "events": [
        {
          "actor_name": "Christina Chortaria",
          "created_at": "2021-06-17T13:52:25",
          "type": "labeled"
        }
      ],
      "pr_html_url": null,
      "action": "updated"
    },
    {
      "created_at": "2021-04-13T13:23:47",
      "updated_at": "2021-04-13T13:23:47",
      "html_url": "https://github.com/pulibrary/bibdata/issues/1234",
      "number": 1234,
      "pull_request_html_url": null,
      "repository_html_url": "https://github.com/pulibrary/bibdata",
      "repository_name": "bibdata",
      "state": "open",
      "title": "Add lando tooling to import backup",
      "user_name": "Christina Chortaria",
      "comments": [],
      "events": [
        {
          "actor_name": "Christina Chortaria",
          "created_at": "2021-06-17T13:55:02",
          "type": "labeled"
        }
      ],
      "pr_html_url": null,
      "action": "updated"
    },
    {
      "created_at": "2021-05-20T20:44:50",
      "updated_at": "2021-05-20T20:44:50",
      "html_url": "https://github.com/pulibrary/bibdata/issues/1345",
      "number": 1345,
      "pull_request_html_url": null,
      "repository_html_url": "https://github.com/pulibrary/bibdata",
      "repository_name": "bibdata",
      "state": "open",
      "title": "Use scopes on the Dump model",
      "user_name": "hackartisan",
      "comments": [],
      "events": [
        {
          "actor_name": "Christina Chortaria",
          "created_at": "2021-06-17T13:55:33",
          "type": "labeled"
        }
      ],
      "pr_html_url": null,
      "action": "updated"
    },
    {
      "created_at": "2021-06-17T13:07:48",
      "updated_at": "2021-06-17T13:07:48",
      "html_url": "https://github.com/pulibrary/bibdata/pull/1429",
      "number": 1429,
      "pull_request_html_url": "https://github.com/pulibrary/bibdata/pull/1429",
      "repository_html_url": "https://github.com/pulibrary/bibdata",
      "repository_name": "bibdata",
      "state": "closed",
      "title": "Rescue any error when fetching a record from figgy",
      "user_name": "hackartisan",
      "comments": [
        {
          "user_name": "Christina Chortaria",
          "updated_at": "2021-06-17T13:20:33",
          "html_url": "https://github.com/pulibrary/bibdata/pull/1429#issuecomment-863233781",
          "body": "@hackartisan circle failed"
        }
      ],
      "events": [
        {
          "actor_name": null,
          "created_at": "2021-06-17T13:20:34",
          "type": "mentioned"
        },
        {
          "actor_name": null,
          "created_at": "2021-06-17T13:20:34",
          "type": "subscribed"
        },
        {
          "actor_name": null,
          "created_at": "2021-06-17T13:26:35",
          "type": "review_dismissed"
        },
        {
          "actor_name": null,
          "created_at": "2021-06-17T13:26:35",
          "type": "head_ref_force_pushed"
        },
        {
          "actor_name": "Christina Chortaria",
          "created_at": "2021-06-17T14:42:11",
          "type": "referenced"
        },
        {
          "actor_name": "Christina Chortaria",
          "created_at": "2021-06-17T14:42:11",
          "type": "merged"
        },
        {
          "actor_name": "Christina Chortaria",
          "created_at": "2021-06-17T14:42:11",
          "type": "closed"
        },
        {
          "actor_name": "Christina Chortaria",
          "created_at": "2021-06-17T14:42:12",
          "type": "head_ref_deleted"
        }
      ],
      "pr_html_url": "https://github.com/pulibrary/bibdata/pull/1429",
      "action": "pull_request_closed"
    },
    {
      "created_at": "2021-06-17T15:55:11",
      "updated_at": "2021-06-17T15:55:11",
      "html_url": "https://github.com/pulibrary/bibdata/issues/1432",
      "number": 1432,
      "pull_request_html_url": null,
      "repository_html_url": "https://github.com/pulibrary/bibdata",
      "repository_name": "bibdata",
      "state": "open",
      "title": "Handle possible 429 from bibdata in figgy",
      "user_name": "hackartisan",
      "comments": [],
      "events": [
        {
          "actor_name": null,
          "created_at": "2021-06-17T15:55:11",
          "type": "labeled"
        }
      ],
      "pr_html_url": null,
      "action": "created"
    },
    {
      "created_at": "2021-06-15T18:44:12",
      "updated_at": "2021-06-15T18:44:12",
      "html_url": "https://github.com/pulibrary/bibdata/issues/1421",
      "number": 1421,
      "pull_request_html_url": null,
      "repository_html_url": "https://github.com/pulibrary/bibdata",
      "repository_name": "bibdata",
      "state": "open",
      "title": "SCSB dump files empty",
      "user_name": "Hector Correa",
      "comments": [
        {
          "user_name": "Trey Pendragon",
          "updated_at": "2021-06-16T22:36:36",
          "html_url": "https://github.com/pulibrary/bibdata/issues/1421#issuecomment-862775228",
          "body": "I think this is because prod isn't hooked up to the SCSB production bucket yet (didn't want to push partner updates out from these boxes.)\r\n\r\nSee https://github.com/pulibrary/princeton_ansible/blob/c7bce40ad04daa1048ff84a89d4803bae18f6998/group_vars/bibdata/alma_production.yml#L97-L102\r\n\r\nvs \r\n\r\nhttps://github.com/pulibrary/princeton_ansible/blob/c7bce40ad04daa1048ff84a89d4803bae18f6998/group_vars/bibdata/production.yml#L127-L134\r\n\r\nWe can either just disable submit collection (maybe that's done already?) and hook this up to the right spot, or add it to the list of things to do for go-live."
        },
        {
          "user_name": "Christina Chortaria",
          "updated_at": "2021-06-16T22:38:15",
          "html_url": "https://github.com/pulibrary/bibdata/issues/1421#issuecomment-862776398",
          "body": "These are not the Princeton recap but the Recap Partner files we pull from SCSB."
        },
        {
          "user_name": "Trey Pendragon",
          "updated_at": "2021-06-16T22:39:30",
          "html_url": "https://github.com/pulibrary/bibdata/issues/1421#issuecomment-862776997",
          "body": "Yes, I know, but the SCSB bucket configuration comes from the same place."
        },
        {
          "user_name": "Christina Chortaria",
          "updated_at": "2021-06-16T22:40:11",
          "html_url": "https://github.com/pulibrary/bibdata/issues/1421#issuecomment-862777332",
          "body": "yes I see what you are saying. That it is disabled so that we dont submit princeton files to recap. "
        },
        {
          "user_name": "hackartisan",
          "updated_at": "2021-06-17T14:47:34",
          "html_url": "https://github.com/pulibrary/bibdata/issues/1421#issuecomment-863304242",
          "body": "Ah, that makes sense. Then I think we may need to split out configuration for reads vs. writes. Because we need to be able to pull in the partner data and index it before we are able to push our own data."
        }
      ],
      "events": [
        {
          "actor_name": "Christina Chortaria",
          "created_at": "2021-06-16T22:41:43",
          "type": "unlabeled"
        },
        {
          "actor_name": "Trey Pendragon",
          "created_at": "2021-06-17T16:26:34",
          "type": "assigned"
        }
      ],
      "pr_html_url": null,
      "action": "updated"
    },
    {
      "created_at": "2021-01-19T15:29:52",
      "updated_at": "2021-01-19T15:29:52",
      "html_url": "https://github.com/pulibrary/bibdata/issues/983",
      "number": 983,
      "pull_request_html_url": null,
      "repository_html_url": "https://github.com/pulibrary/bibdata",
      "repository_name": "bibdata",
      "state": "open",
      "title": "Build, provision, deploy production alma infrastructure",
      "user_name": "hackartisan",
      "comments": [
        {
          "user_name": "Trey Pendragon",
          "updated_at": "2021-06-16T22:20:05",
          "html_url": "https://github.com/pulibrary/bibdata/issues/983#issuecomment-845473058",
          "body": "This is what's configured now.\r\n\r\n![Current State](https://user-images.githubusercontent.com/2806645/119047890-58600f00-b973-11eb-84bd-c369bf036390.png)\r\n\r\nMissing steps:\r\n- [x] Merge https://github.com/pulibrary/bibdata/pull/1344\r\n- [x] Set up cert/name/load balancer for catalog-alma.princeton.edu\r\n- [x] Fix Redis configuration for bibdata1/2/worker1 to use a single redis instance for Sidekiq.\r\n"
        }
      ],
      "events": [],
      "pr_html_url": null,
      "action": "updated"
    },
    {
      "created_at": "2021-06-17T16:52:42",
      "updated_at": "2021-06-17T16:52:42",
      "html_url": "https://github.com/pulibrary/bibdata/pull/1433",
      "number": 1433,
      "pull_request_html_url": "https://github.com/pulibrary/bibdata/pull/1433",
      "repository_html_url": "https://github.com/pulibrary/bibdata",
      "repository_name": "bibdata",
      "state": "open",
      "title": "Add separate S3 configuration for partner updates.",
      "user_name": "Trey Pendragon",
      "comments": [],
      "events": [],
      "pr_html_url": "https://github.com/pulibrary/bibdata/pull/1433",
      "action": "pull_request_open"
    },
    {
      "created_at": "2021-06-17T13:18:41",
      "updated_at": "2021-06-17T13:18:41",
      "html_url": "https://github.com/pulibrary/bibdata/pull/1430",
      "number": 1430,
      "pull_request_html_url": "https://github.com/pulibrary/bibdata/pull/1430",
      "repository_html_url": "https://github.com/pulibrary/bibdata",
      "repository_name": "bibdata",
      "state": "open",
      "title": "[WIP] Replaces fixtures using responses from the Alma API",
      "user_name": "James R. Griffin III",
      "comments": [],
      "events": [
        {
          "actor_name": "James R. Griffin III",
          "created_at": "2021-06-17T17:02:34",
          "type": "head_ref_force_pushed"
        },
        {
          "actor_name": "James R. Griffin III",
          "created_at": "2021-06-17T17:05:40",
          "type": "head_ref_force_pushed"
        }
      ],
      "pr_html_url": "https://github.com/pulibrary/bibdata/pull/1430",
      "action": "pull_request_open"
    },
    {
      "created_at": "2021-04-14T17:27:33",
      "updated_at": "2021-04-14T17:27:33",
      "html_url": "https://github.com/pulibrary/bibdata/issues/1246",
      "number": 1246,
      "pull_request_html_url": null,
      "repository_html_url": "https://github.com/pulibrary/bibdata",
      "repository_name": "bibdata",
      "state": "open",
      "title": "Update fixtures for skipped holdings tests in traject config spec",
      "user_name": "Eliot Jordan",
      "comments": [],
      "events": [
        {
          "actor_name": null,
          "created_at": "2021-06-17T19:41:16",
          "type": "renamed"
        }
      ],
      "pr_html_url": null,
      "action": "updated"
    },
    {
      "created_at": "2021-03-30T20:04:09",
      "updated_at": "2021-03-30T20:04:09",
      "html_url": "https://github.com/pulibrary/bibdata/issues/1184",
      "number": 1184,
      "pull_request_html_url": null,
      "repository_html_url": "https://github.com/pulibrary/bibdata",
      "repository_name": "bibdata",
      "state": "closed",
      "title": "Create a guide document for the catalog-alma-qa QA testing",
      "user_name": "Christina Chortaria",
      "comments": [],
      "events": [
        {
          "actor_name": null,
          "created_at": "2021-06-17T19:45:01",
          "type": "closed"
        }
      ],
      "pr_html_url": null,
      "action": "closed"
    },
    {
      "created_at": "2021-06-14T19:32:28",
      "updated_at": "2021-06-14T19:32:28",
      "html_url": "https://github.com/pulibrary/bibdata/issues/1417",
      "number": 1417,
      "pull_request_html_url": null,
      "repository_html_url": "https://github.com/pulibrary/bibdata",
      "repository_name": "bibdata",
      "state": "open",
      "title": "Add an alma worker for staging",
      "user_name": "hackartisan",
      "comments": [],
      "events": [
        {
          "actor_name": "Christina Chortaria",
          "created_at": "2021-06-17T13:23:33",
          "type": "labeled"
        },
        {
          "actor_name": "Christina Chortaria",
          "created_at": "2021-06-17T19:47:29",
          "type": "unassigned"
        }
      ],
      "pr_html_url": null,
      "action": "updated"
    },
    {
      "created_at": "2021-02-10T21:58:39",
      "updated_at": "2021-02-10T21:58:39",
      "html_url": "https://github.com/pulibrary/bibdata/issues/1071",
      "number": 1071,
      "pull_request_html_url": null,
      "repository_html_url": "https://github.com/pulibrary/bibdata",
      "repository_name": "bibdata",
      "state": "open",
      "title": "Enable copy number test with new alma fixture",
      "user_name": "Christina Chortaria",
      "comments": [],
      "events": [
        {
          "actor_name": null,
          "created_at": "2021-06-17T19:58:51",
          "type": "renamed"
        }
      ],
      "pr_html_url": null,
      "action": "updated"
    },
    {
      "created_at": "2021-03-31T13:56:58",
      "updated_at": "2021-03-31T13:56:58",
      "html_url": "https://github.com/pulibrary/bibdata/issues/1185",
      "number": 1185,
      "pull_request_html_url": null,
      "repository_html_url": "https://github.com/pulibrary/bibdata",
      "repository_name": "bibdata",
      "state": "closed",
      "title": "Research: barcode#scsb can we replace any of the alma API calls with solr lookups?",
      "user_name": "hackartisan",
      "comments": [],
      "events": [
        {
          "actor_name": null,
          "created_at": "2021-06-17T20:11:41",
          "type": "closed"
        }
      ],
      "pr_html_url": null,
      "action": "closed"
    },
    {
      "created_at": "2021-01-26T19:39:27",
      "updated_at": "2021-01-26T19:39:27",
      "html_url": "https://github.com/pulibrary/bibdata/issues/1007",
      "number": 1007,
      "pull_request_html_url": null,
      "repository_html_url": "https://github.com/pulibrary/bibdata",
      "repository_name": "bibdata",
      "state": "open",
      "title": "Test traject indexing of contained_in_s on a fixture with 2 different host records",
      "user_name": "hackartisan",
      "comments": [],
      "events": [],
      "pr_html_url": null,
      "action": "updated"
    },
    {
      "created_at": "2021-03-26T16:27:52",
      "updated_at": "2021-03-26T16:27:52",
      "html_url": "https://github.com/pulibrary/bibdata/issues/1165",
      "number": 1165,
      "pull_request_html_url": null,
      "repository_html_url": "https://github.com/pulibrary/bibdata",
      "repository_name": "bibdata",
      "state": "open",
      "title": "Remove the Hours Location feature",
      "user_name": "Christina Chortaria",
      "comments": [],
      "events": [
        {
          "actor_name": null,
          "created_at": "2021-06-17T20:14:59",
          "type": "renamed"
        },
        {
          "actor_name": null,
          "created_at": "2021-06-17T20:15:02",
          "type": "unlabeled"
        },
        {
          "actor_name": null,
          "created_at": "2021-06-17T20:15:07",
          "type": "labeled"
        }
      ],
      "pr_html_url": null,
      "action": "updated"
    },
    {
      "created_at": "2021-03-26T16:25:02",
      "updated_at": "2021-03-26T16:25:02",
      "html_url": "https://github.com/pulibrary/bibdata/issues/1164",
      "number": 1164,
      "pull_request_html_url": null,
      "repository_html_url": "https://github.com/pulibrary/bibdata",
      "repository_name": "bibdata",
      "state": "open",
      "title": "Rename the column Holding Library in the Holding Locations table.",
      "user_name": "Christina Chortaria",
      "comments": [],
      "events": [
        {
          "actor_name": null,
          "created_at": "2021-06-17T20:15:30",
          "type": "labeled"
        },
        {
          "actor_name": null,
          "created_at": "2021-06-17T20:15:32",
          "type": "unlabeled"
        }
      ],
      "pr_html_url": null,
      "action": "updated"
    },
    {
      "created_at": "2020-12-21T17:11:04",
      "updated_at": "2020-12-21T17:11:04",
      "html_url": "https://github.com/pulibrary/bibdata/issues/950",
      "number": 950,
      "pull_request_html_url": null,
      "repository_html_url": "https://github.com/pulibrary/bibdata",
      "repository_name": "bibdata",
      "state": "closed",
      "title": "Update the 773w field in the Alma records",
      "user_name": "Christina Chortaria",
      "comments": [
        {
          "user_name": "hackartisan",
          "updated_at": "2021-06-17T20:15:49",
          "html_url": "https://github.com/pulibrary/bibdata/issues/950#issuecomment-863534453",
          "body": "done"
        }
      ],
      "events": [
        {
          "actor_name": null,
          "created_at": "2021-06-17T20:15:49",
          "type": "closed"
        }
      ],
      "pr_html_url": null,
      "action": "closed"
    },
    {
      "created_at": "2021-04-01T20:46:39",
      "updated_at": "2021-04-01T20:46:39",
      "html_url": "https://github.com/pulibrary/bibdata/issues/1198",
      "number": 1198,
      "pull_request_html_url": null,
      "repository_html_url": "https://github.com/pulibrary/bibdata",
      "repository_name": "bibdata",
      "state": "open",
      "title": "Index temp locations",
      "user_name": "hackartisan",
      "comments": [],
      "events": [
        {
          "actor_name": null,
          "created_at": "2021-06-17T20:16:15",
          "type": "unlabeled"
        }
      ],
      "pr_html_url": null,
      "action": "updated"
    },
    {
      "created_at": "2021-03-31T21:13:16",
      "updated_at": "2021-03-31T21:13:16",
      "html_url": "https://github.com/pulibrary/bibdata/issues/1193",
      "number": 1193,
      "pull_request_html_url": null,
      "repository_html_url": "https://github.com/pulibrary/bibdata",
      "repository_name": "bibdata",
      "state": "open",
      "title": "Remove locations forms from the bibdata UI",
      "user_name": "Christina Chortaria",
      "comments": [],
      "events": [
        {
          "actor_name": null,
          "created_at": "2021-06-17T20:16:37",
          "type": "renamed"
        },
        {
          "actor_name": null,
          "created_at": "2021-06-17T20:16:41",
          "type": "unlabeled"
        },
        {
          "actor_name": null,
          "created_at": "2021-06-17T20:16:50",
          "type": "labeled"
        }
      ],
      "pr_html_url": null,
      "action": "updated"
    },
    {
      "created_at": "2020-08-06T13:13:10",
      "updated_at": "2020-08-06T13:13:10",
      "html_url": "https://github.com/pulibrary/bibdata/issues/731",
      "number": 731,
      "pull_request_html_url": null,
      "repository_html_url": "https://github.com/pulibrary/bibdata",
      "repository_name": "bibdata",
      "state": "closed",
      "title": "Fix leaders on records from alma publishing job",
      "user_name": "Christina Chortaria",
      "comments": [
        {
          "user_name": "hackartisan",
          "updated_at": "2021-06-17T20:17:44",
          "html_url": "https://github.com/pulibrary/bibdata/issues/731#issuecomment-863535917",
          "body": "Revisit if we decide to try using marc21."
        }
      ],
      "events": [
        {
          "actor_name": null,
          "created_at": "2021-06-17T20:17:44",
          "type": "closed"
        }
      ],
      "pr_html_url": null,
      "action": "closed"
    },
    {
      "created_at": "2021-04-02T13:31:33",
      "updated_at": "2021-04-02T13:31:33",
      "html_url": "https://github.com/pulibrary/bibdata/issues/1199",
      "number": 1199,
      "pull_request_html_url": null,
      "repository_html_url": "https://github.com/pulibrary/bibdata",
      "repository_name": "bibdata",
      "state": "open",
      "title": "Index remote storage locations",
      "user_name": "hackartisan",
      "comments": [],
      "events": [
        {
          "actor_name": null,
          "created_at": "2021-06-17T20:18:23",
          "type": "unlabeled"
        }
      ],
      "pr_html_url": null,
      "action": "updated"
    },
    {
      "created_at": "2021-04-16T13:10:32",
      "updated_at": "2021-04-16T13:10:32",
      "html_url": "https://github.com/pulibrary/bibdata/issues/1260",
      "number": 1260,
      "pull_request_html_url": null,
      "repository_html_url": "https://github.com/pulibrary/bibdata",
      "repository_name": "bibdata",
      "state": "open",
      "title": "Load test the alma-based catalog",
      "user_name": "hackartisan",
      "comments": [],
      "events": [],
      "pr_html_url": null,
      "action": "updated"
    },
    {
      "created_at": "2020-04-23T14:55:50",
      "updated_at": "2020-04-23T14:55:50",
      "html_url": "https://github.com/pulibrary/bibdata/issues/635",
      "number": 635,
      "pull_request_html_url": null,
      "repository_html_url": "https://github.com/pulibrary/bibdata",
      "repository_name": "bibdata",
      "state": "closed",
      "title": "Ensure interoperability with firestone_locator",
      "user_name": "Kate Lynch",
      "comments": [
        {
          "user_name": "hackartisan",
          "updated_at": "2021-06-17T20:19:42",
          "html_url": "https://github.com/pulibrary/bibdata/issues/635#issuecomment-863537405",
          "body": "covered by another ticket"
        }
      ],
      "events": [
        {
          "actor_name": null,
          "created_at": "2021-06-17T20:19:43",
          "type": "closed"
        }
      ],
      "pr_html_url": null,
      "action": "closed"
    },
    {
      "created_at": "2020-04-30T19:42:15",
      "updated_at": "2020-04-30T19:42:15",
      "html_url": "https://github.com/pulibrary/bibdata/issues/638",
      "number": 638,
      "pull_request_html_url": null,
      "repository_html_url": "https://github.com/pulibrary/bibdata",
      "repository_name": "bibdata",
      "state": "open",
      "title": "Testing new releases of Alma",
      "user_name": "Esmé Cowles",
      "comments": [],
      "events": [
        {
          "actor_name": null,
          "created_at": "2021-06-17T20:20:04",
          "type": "unlabeled"
        },
        {
          "actor_name": null,
          "created_at": "2021-06-17T20:20:25",
          "type": "unlabeled"
        }
      ],
      "pr_html_url": null,
      "action": "updated"
    },
    {
      "created_at": "2020-05-06T20:30:27",
      "updated_at": "2020-05-06T20:30:27",
      "html_url": "https://github.com/pulibrary/bibdata/issues/647",
      "number": 647,
      "pull_request_html_url": null,
      "repository_html_url": "https://github.com/pulibrary/bibdata",
      "repository_name": "bibdata",
      "state": "closed",
      "title": "Post a sample of records with location 'f'",
      "user_name": "Christina Chortaria",
      "comments": [],
      "events": [
        {
          "actor_name": null,
          "created_at": "2021-06-17T20:20:34",
          "type": "closed"
        }
      ],
      "pr_html_url": null,
      "action": "closed"
    },
    {
      "created_at": "2020-09-17T15:16:51",
      "updated_at": "2020-09-17T15:16:51",
      "html_url": "https://github.com/pulibrary/bibdata/issues/794",
      "number": 794,
      "pull_request_html_url": null,
      "repository_html_url": "https://github.com/pulibrary/bibdata",
      "repository_name": "bibdata",
      "state": "closed",
      "title": "Test due date variations in availability controller",
      "user_name": "hackartisan",
      "comments": [
        {
          "user_name": "hackartisan",
          "updated_at": "2021-06-17T20:21:05",
          "html_url": "https://github.com/pulibrary/bibdata/issues/794#issuecomment-863538489",
          "body": "we don't have due dates anymore"
        }
      ],
      "events": [
        {
          "actor_name": null,
          "created_at": "2021-06-17T20:21:05",
          "type": "closed"
        }
      ],
      "pr_html_url": null,
      "action": "closed"
    },
    {
      "created_at": "2020-04-24T15:50:00",
      "updated_at": "2020-04-24T15:50:00",
      "html_url": "https://github.com/pulibrary/bibdata/issues/641",
      "number": 641,
      "pull_request_html_url": null,
      "repository_html_url": "https://github.com/pulibrary/bibdata",
      "repository_name": "bibdata",
      "state": "closed",
      "title": "Retrieve full availability using the Alma API",
      "user_name": "Christina Chortaria",
      "comments": [],
      "events": [
        {
          "actor_name": null,
          "created_at": "2021-06-17T20:21:20",
          "type": "closed"
        }
      ],
      "pr_html_url": null,
      "action": "closed"
    },
    {
      "created_at": "2020-07-24T15:45:37",
      "updated_at": "2020-07-24T15:45:37",
      "html_url": "https://github.com/pulibrary/bibdata/issues/721",
      "number": 721,
      "pull_request_html_url": null,
      "repository_html_url": "https://github.com/pulibrary/bibdata",
      "repository_name": "bibdata",
      "state": "closed",
      "title": "List pieces of information from the alma record that we want to include in the bibdata call",
      "user_name": "Christina Chortaria",
      "comments": [
        {
          "user_name": "hackartisan",
          "updated_at": "2021-06-17T20:22:02",
          "html_url": "https://github.com/pulibrary/bibdata/issues/721#issuecomment-863539092",
          "body": "We worked to ensure APIs only returned fields that clients needed."
        }
      ],
      "events": [
        {
          "actor_name": null,
          "created_at": "2021-06-17T20:22:02",
          "type": "closed"
        }
      ],
      "pr_html_url": null,
      "action": "closed"
    },
    {
      "created_at": "2020-08-13T13:51:24",
      "updated_at": "2020-08-13T13:51:24",
      "html_url": "https://github.com/pulibrary/bibdata/issues/749",
      "number": 749,
      "pull_request_html_url": null,
      "repository_html_url": "https://github.com/pulibrary/bibdata",
      "repository_name": "bibdata",
      "state": "closed",
      "title": "Availability gap analysis",
      "user_name": "Christina Chortaria",
      "comments": [],
      "events": [
        {
          "actor_name": null,
          "created_at": "2021-06-17T20:22:13",
          "type": "closed"
        }
      ],
      "pr_html_url": null,
      "action": "closed"
    },
    {
      "created_at": "2021-06-15T17:44:30",
      "updated_at": "2021-06-15T17:44:30",
      "html_url": "https://github.com/pulibrary/bibdata/pull/1419",
      "number": 1419,
      "pull_request_html_url": "https://github.com/pulibrary/bibdata/pull/1419",
      "repository_html_url": "https://github.com/pulibrary/bibdata",
      "repository_name": "bibdata",
      "state": "closed",
      "title": "Adding modified Alma fixtures in order to ensure that the test suites for advanced_location_s and location_code_s/location_display are now passing",
      "user_name": "James R. Griffin III",
      "comments": [],
      "events": [
        {
          "actor_name": "James R. Griffin III",
          "created_at": "2021-06-17T18:28:09",
          "type": "head_ref_force_pushed"
        },
        {
          "actor_name": "James R. Griffin III",
          "created_at": "2021-06-17T19:04:13",
          "type": "review_requested"
        },
        {
          "actor_name": "Christina Chortaria",
          "created_at": "2021-06-17T20:31:00",
          "type": "referenced"
        },
        {
          "actor_name": "Christina Chortaria",
          "created_at": "2021-06-17T20:31:00",
          "type": "merged"
        },
        {
          "actor_name": "Christina Chortaria",
          "created_at": "2021-06-17T20:31:00",
          "type": "closed"
        },
        {
          "actor_name": "Christina Chortaria",
          "created_at": "2021-06-17T20:31:00",
          "type": "head_ref_deleted"
        }
      ],
      "pr_html_url": "https://github.com/pulibrary/bibdata/pull/1419",
      "action": "pull_request_closed"
    },
    {
      "created_at": "2020-12-01T20:18:55",
      "updated_at": "2020-12-01T20:18:55",
      "html_url": "https://github.com/pulibrary/bibdata/pull/905",
      "number": 905,
      "pull_request_html_url": "https://github.com/pulibrary/bibdata/pull/905",
      "repository_html_url": "https://github.com/pulibrary/bibdata",
      "repository_name": "bibdata",
      "state": "open",
      "title": "[Do not merge] Alma Migration",
      "user_name": "Trey Pendragon",
      "comments": [],
      "events": [
        {
          "actor_name": "Trey Pendragon",
          "created_at": "2021-06-17T15:42:02",
          "type": "deployed"
        },
        {
          "actor_name": "Trey Pendragon",
          "created_at": "2021-06-17T16:50:56",
          "type": "deployed"
        }
      ],
      "pr_html_url": "https://github.com/pulibrary/bibdata/pull/905",
      "action": "pull_request_open"
    },
    {
      "created_at": "2021-06-17T20:53:20",
      "updated_at": "2021-06-17T20:53:20",
      "html_url": "https://github.com/pulibrary/bibdata/issues/1435",
      "number": 1435,
      "pull_request_html_url": null,
      "repository_html_url": "https://github.com/pulibrary/bibdata",
      "repository_name": "bibdata",
      "state": "open",
      "title": "Traject Rake tasks may not block while files are being generated",
      "user_name": "James R. Griffin III",
      "comments": [],
      "events": [
        {
          "actor_name": "James R. Griffin III",
          "created_at": "2021-06-17T20:53:59",
          "type": "renamed"
        },
        {
          "actor_name": "James R. Griffin III",
          "created_at": "2021-06-17T20:58:34",
          "type": "labeled"
        },
        {
          "actor_name": "James R. Griffin III",
          "created_at": "2021-06-17T20:58:42",
          "type": "labeled"
        }
      ],
      "pr_html_url": null,
      "action": "created"
    },
    {
      "created_at": "2021-06-17T20:57:55",
      "updated_at": "2021-06-17T20:57:55",
      "html_url": "https://github.com/pulibrary/bibdata/pull/1436",
      "number": 1436,
      "pull_request_html_url": "https://github.com/pulibrary/bibdata/pull/1436",
      "repository_html_url": "https://github.com/pulibrary/bibdata",
      "repository_name": "bibdata",
      "state": "open",
      "title": "Update location map generator, update locations with latest changes, update templates,update availability to include library name in front.",
      "user_name": "Christina Chortaria",
      "comments": [
        {
          "user_name": "Christina Chortaria",
          "updated_at": "2021-06-18T01:31:58",
          "html_url": "https://github.com/pulibrary/bibdata/pull/1436#issuecomment-863666056",
          "body": "When you merge this PR you will need to update the locations on bibdata-alma-staging. \r\n- enter the rails console in the VM and run `LocationDataService.delete_existing_and_repopulate`\r\nFor local development you will need to generate from templates since the templates have been updated. This happens when you run `bundle exec rake servers:start`.\r\n"
        }
      ],
      "events": [
        {
          "actor_name": "Christina Chortaria",
          "created_at": "2021-06-17T20:59:58",
          "type": "convert_to_draft"
        },
        {
          "actor_name": "Christina Chortaria",
          "created_at": "2021-06-18T00:14:33",
          "type": "head_ref_force_pushed"
        },
        {
          "actor_name": "Christina Chortaria",
          "created_at": "2021-06-18T01:08:55",
          "type": "head_ref_force_pushed"
        },
        {
          "actor_name": "Christina Chortaria",
          "created_at": "2021-06-18T01:32:10",
          "type": "ready_for_review"
        },
        {
          "actor_name": "Christina Chortaria",
          "created_at": "2021-06-18T01:32:39",
          "type": "renamed"
        }
      ],
      "pr_html_url": "https://github.com/pulibrary/bibdata/pull/1436",
      "action": "pull_request_open"
    },
    {
      "created_at": "2021-06-17T19:03:41",
      "updated_at": "2021-06-17T19:03:41",
      "html_url": "https://github.com/pulibrary/bibdata/issues/1434",
      "number": 1434,
      "pull_request_html_url": null,
      "repository_html_url": "https://github.com/pulibrary/bibdata",
      "repository_name": "bibdata",
      "state": "open",
      "title": "If holding library name is blank, location display should not fall back to the library name",
      "user_name": "Christina Chortaria",
      "comments": [],
      "events": [
        {
          "actor_name": "Christina Chortaria",
          "created_at": "2021-06-17T19:03:41",
          "type": "labeled"
        },
        {
          "actor_name": "Christina Chortaria",
          "created_at": "2021-06-17T19:03:41",
          "type": "labeled"
        },
        {
          "actor_name": "Christina Chortaria",
          "created_at": "2021-06-17T19:03:42",
          "type": "assigned"
        },
        {
          "actor_name": "Christina Chortaria",
          "created_at": "2021-06-18T01:33:41",
          "type": "unlabeled"
        },
        {
          "actor_name": "Christina Chortaria",
          "created_at": "2021-06-18T01:33:41",
          "type": "labeled"
        },
        {
          "actor_name": "Christina Chortaria",
          "created_at": "2021-06-18T01:34:16",
          "type": "unlabeled"
        },
        {
          "actor_name": "Christina Chortaria",
          "created_at": "2021-06-18T01:34:16",
          "type": "labeled"
        }
      ],
      "pr_html_url": null,
      "action": "created"
    },
    {
      "created_at": "2021-06-18T01:02:53",
      "updated_at": "2021-06-18T01:02:53",
      "html_url": "https://github.com/pulibrary/bibdata/issues/1437",
      "number": 1437,
      "pull_request_html_url": null,
      "repository_html_url": "https://github.com/pulibrary/bibdata",
      "repository_name": "bibdata",
      "state": "open",
      "title": "Update availability on the item and holding level to include the library in front of the location label",
      "user_name": "Christina Chortaria",
      "comments": [],
      "events": [
        {
          "actor_name": "Christina Chortaria",
          "created_at": "2021-06-18T01:02:53",
          "type": "labeled"
        },
        {
          "actor_name": "Christina Chortaria",
          "created_at": "2021-06-18T01:02:53",
          "type": "assigned"
        },
        {
          "actor_name": "Christina Chortaria",
          "created_at": "2021-06-18T01:08:57",
          "type": "referenced"
        },
        {
          "actor_name": "Christina Chortaria",
          "created_at": "2021-06-18T01:33:22",
          "type": "labeled"
        },
        {
          "actor_name": "Christina Chortaria",
          "created_at": "2021-06-18T01:34:34",
          "type": "unlabeled"
        },
        {
          "actor_name": "Christina Chortaria",
          "created_at": "2021-06-18T01:34:34",
          "type": "labeled"
        }
      ],
      "pr_html_url": null,
      "action": "created"
    },
    {
      "created_at": "2021-06-17T13:48:43",
      "updated_at": "2021-06-17T13:48:43",
      "html_url": "https://github.com/pulibrary/bibdata/issues/1431",
      "number": 1431,
      "pull_request_html_url": null,
      "repository_html_url": "https://github.com/pulibrary/bibdata",
      "repository_name": "bibdata",
      "state": "open",
      "title": "Reload locations and update templates before the first Alma production full index",
      "user_name": "Christina Chortaria",
      "comments": [],
      "events": [
        {
          "actor_name": "Christina Chortaria",
          "created_at": "2021-06-17T13:48:43",
          "type": "labeled"
        },
        {
          "actor_name": "Christina Chortaria",
          "created_at": "2021-06-17T19:45:37",
          "type": "assigned"
        },
        {
          "actor_name": "Christina Chortaria",
          "created_at": "2021-06-17T20:39:59",
          "type": "referenced"
        },
        {
          "actor_name": "Christina Chortaria",
          "created_at": "2021-06-18T00:14:32",
          "type": "referenced"
        },
        {
          "actor_name": "Christina Chortaria",
          "created_at": "2021-06-18T01:08:55",
          "type": "referenced"
        },
        {
          "actor_name": "Christina Chortaria",
          "created_at": "2021-06-18T01:33:58",
          "type": "labeled"
        },
        {
          "actor_name": "Christina Chortaria",
          "created_at": "2021-06-18T01:35:11",
          "type": "unlabeled"
        },
        {
          "actor_name": "Christina Chortaria",
          "created_at": "2021-06-18T01:35:11",
          "type": "labeled"
        }
      ],
      "pr_html_url": null,
      "action": "created"
    },
    {
      "created_at": "2021-06-16T15:14:58",
      "updated_at": "2021-06-16T15:14:58",
      "html_url": "https://github.com/pulibrary/bibdata/pull/1425",
      "number": 1425,
      "pull_request_html_url": "https://github.com/pulibrary/bibdata/pull/1425",
      "repository_html_url": "https://github.com/pulibrary/bibdata",
      "repository_name": "bibdata",
      "state": "open",
      "title": "Adds rake task to register a local PARTNER_RECAP file into the database",
      "user_name": "Hector Correa",
      "comments": [],
      "events": [
        {
          "actor_name": "Christina Chortaria",
          "created_at": "2021-06-18T01:42:21",
          "type": "review_dismissed"
        }
      ],
      "pr_html_url": "https://github.com/pulibrary/bibdata/pull/1425",
      "action": "pull_request_open"
    },
    {
      "created_at": "2021-05-26T15:04:28",
      "updated_at": "2021-05-26T15:04:28",
      "html_url": "https://github.com/pulibrary/bibdata/issues/1362",
      "number": 1362,
      "pull_request_html_url": null,
      "repository_html_url": "https://github.com/pulibrary/bibdata",
      "repository_name": "bibdata",
      "state": "open",
      "title": "Step through browse list generation and document for go-live",
      "user_name": "hackartisan",
      "comments": [],
      "events": [
        {
          "actor_name": "Christina Chortaria",
          "created_at": "2021-06-18T01:43:19",
          "type": "unassigned"
        }
      ],
      "pr_html_url": null,
      "action": "updated"
    }
  ],
  "connect-four": [
    {
      "created_at": "2021-06-17T13:44:14",
      "updated_at": "2021-06-17T13:44:14",
      "html_url": "https://github.com/pulibrary/connect-four/pull/1",
      "number": 1,
      "pull_request_html_url": "https://github.com/pulibrary/connect-four/pull/1",
      "repository_html_url": "https://github.com/pulibrary/connect-four",
      "repository_name": "connect-four",
      "state": "closed",
      "title": "Create game",
      "user_name": "Zaynab Masood",
      "comments": [],
      "events": [
        {
          "actor_name": null,
          "created_at": "2021-06-17T13:46:21",
          "type": "deployed"
        },
        {
          "actor_name": "Zaynab Masood",
          "created_at": "2021-06-17T13:46:26",
          "type": "referenced"
        },
        {
          "actor_name": "Zaynab Masood",
          "created_at": "2021-06-17T13:46:26",
          "type": "merged"
        },
        {
          "actor_name": "Zaynab Masood",
          "created_at": "2021-06-17T13:46:26",
          "type": "closed"
        },
        {
          "actor_name": "Zaynab Masood",
          "created_at": "2021-06-17T13:46:35",
          "type": "head_ref_deleted"
        }
      ],
      "pr_html_url": "https://github.com/pulibrary/connect-four/pull/1",
      "action": "pull_request_closed"
    }
  ],
  "dspace-development": [
    {
      "created_at": "2021-06-17T17:56:51",
      "updated_at": "2021-06-17T17:56:51",
      "html_url": "https://github.com/pulibrary/dspace-development/issues/440",
      "number": 440,
      "pull_request_html_url": null,
      "repository_html_url": "https://github.com/pulibrary/dspace-development",
      "repository_name": "dspace-development",
      "state": "closed",
      "title": "Ensure that OAR users jbolton and ribrahem has metadata editing privileges for the LISD Collection",
      "user_name": "James R. Griffin III",
      "comments": [],
      "events": [
        {
          "actor_name": "James R. Griffin III",
          "created_at": "2021-06-17T17:56:55",
          "type": "assigned"
        },
        {
          "actor_name": "James R. Griffin III",
          "created_at": "2021-06-17T17:57:08",
          "type": "labeled"
        },
        {
          "actor_name": "James R. Griffin III",
          "created_at": "2021-06-17T17:57:08",
          "type": "labeled"
        },
        {
          "actor_name": "James R. Griffin III",
          "created_at": "2021-06-17T19:16:38",
          "type": "renamed"
        },
        {
          "actor_name": "James R. Griffin III",
          "created_at": "2021-06-17T19:52:01",
          "type": "closed"
        }
      ],
      "pr_html_url": null,
      "action": "created"
    }
  ],
  "figgy": [
    {
      "created_at": "2021-06-17T15:37:19",
      "updated_at": "2021-06-17T15:37:19",
      "html_url": "https://github.com/pulibrary/figgy/issues/4548",
      "number": 4548,
      "pull_request_html_url": null,
      "repository_html_url": "https://github.com/pulibrary/figgy",
      "repository_name": "figgy",
      "state": "open",
      "title": "Add a reference URL field for Nomisma to coins",
      "user_name": "Kate Lynch",
      "comments": [],
      "events": [
        {
          "actor_name": "Kate Lynch",
          "created_at": "2021-06-17T15:37:40",
          "type": "labeled"
        }
      ],
      "pr_html_url": null,
      "action": "created"
    },
    {
      "created_at": "2021-06-17T15:52:39",
      "updated_at": "2021-06-17T15:52:39",
      "html_url": "https://github.com/pulibrary/figgy/issues/4549",
      "number": 4549,
      "pull_request_html_url": null,
      "repository_html_url": "https://github.com/pulibrary/figgy",
      "repository_name": "figgy",
      "state": "open",
      "title": "Rake task to change voyager IDs to Alma IDs",
      "user_name": "hackartisan",
      "comments": [],
      "events": [],
      "pr_html_url": null,
      "action": "created"
    },
    {
      "created_at": "2020-08-03T14:26:43",
      "updated_at": "2020-08-03T14:26:43",
      "html_url": "https://github.com/pulibrary/figgy/issues/4140",
      "number": 4140,
      "pull_request_html_url": null,
      "repository_html_url": "https://github.com/pulibrary/figgy",
      "repository_name": "figgy",
      "state": "closed",
      "title": "Share data coin data with Nomisma",
      "user_name": "Kevin McElwee",
      "comments": [
        {
          "user_name": "Kevin McElwee",
          "updated_at": "2021-06-17T20:41:43",
          "html_url": "https://github.com/pulibrary/figgy/issues/4140#issuecomment-863550106",
          "body": "This work is tracked elsewhere"
        }
      ],
      "events": [
        {
          "actor_name": "Kevin McElwee",
          "created_at": "2021-06-17T20:41:43",
          "type": "closed"
        }
      ],
      "pr_html_url": null,
      "action": "closed"
    },
    {
      "created_at": "2021-05-13T23:19:47",
      "updated_at": "2021-05-13T23:19:47",
      "html_url": "https://github.com/pulibrary/figgy/pull/4517",
      "number": 4517,
      "pull_request_html_url": "https://github.com/pulibrary/figgy/pull/4517",
      "repository_html_url": "https://github.com/pulibrary/figgy",
      "repository_name": "figgy",
      "state": "closed",
      "title": "Synchronize with ASpace on Complete",
      "user_name": "Trey Pendragon",
      "comments": [],
      "events": [
        {
          "actor_name": "Trey Pendragon",
          "created_at": "2021-06-17T20:26:50",
          "type": "deployed"
        },
        {
          "actor_name": "Trey Pendragon",
          "created_at": "2021-06-17T22:29:03",
          "type": "referenced"
        },
        {
          "actor_name": "Trey Pendragon",
          "created_at": "2021-06-17T22:29:03",
          "type": "merged"
        },
        {
          "actor_name": "Trey Pendragon",
          "created_at": "2021-06-17T22:29:03",
          "type": "closed"
        },
        {
          "actor_name": "Trey Pendragon",
          "created_at": "2021-06-17T22:29:03",
          "type": "head_ref_deleted"
        }
      ],
      "pr_html_url": "https://github.com/pulibrary/figgy/pull/4517",
      "action": "pull_request_closed"
    }
  ],
  "lib_jobs": [
    {
      "created_at": "2021-06-05T07:53:36",
      "updated_at": "2021-06-05T07:53:36",
      "html_url": "https://github.com/pulibrary/lib_jobs/pull/189",
      "number": 189,
      "pull_request_html_url": "https://github.com/pulibrary/lib_jobs/pull/189",
      "repository_html_url": "https://github.com/pulibrary/lib_jobs",
      "repository_name": "lib_jobs",
      "state": "closed",
      "title": "Bump ws from 6.2.1 to 6.2.2",
      "user_name": "dependabot[bot]",
      "comments": [],
      "events": [
        {
          "actor_name": "Trey Pendragon",
          "created_at": "2021-06-17T11:53:59",
          "type": "deployed"
        },
        {
          "actor_name": null,
          "created_at": "2021-06-17T12:02:07",
          "type": "referenced"
        },
        {
          "actor_name": null,
          "created_at": "2021-06-17T12:02:07",
          "type": "merged"
        },
        {
          "actor_name": null,
          "created_at": "2021-06-17T12:02:07",
          "type": "closed"
        },
        {
          "actor_name": null,
          "created_at": "2021-06-17T12:02:08",
          "type": "head_ref_deleted"
        }
      ],
      "pr_html_url": "https://github.com/pulibrary/lib_jobs/pull/189",
      "action": "pull_request_closed"
    },
    {
      "created_at": "2021-06-16T18:50:51",
      "updated_at": "2021-06-16T18:50:51",
      "html_url": "https://github.com/pulibrary/lib_jobs/pull/196",
      "number": 196,
      "pull_request_html_url": "https://github.com/pulibrary/lib_jobs/pull/196",
      "repository_html_url": "https://github.com/pulibrary/lib_jobs",
      "repository_name": "lib_jobs",
      "state": "closed",
      "title": "Bump postcss from 7.0.35 to 7.0.36",
      "user_name": "dependabot[bot]",
      "comments": [
        {
          "user_name": "carolyncole",
          "updated_at": "2021-06-17T12:02:28",
          "html_url": "https://github.com/pulibrary/lib_jobs/pull/196#issuecomment-863180179",
          "body": "@dependabot rebase"
        }
      ],
      "events": [
        {
          "actor_name": "Dependabot",
          "created_at": "2021-06-17T12:02:28",
          "type": "mentioned"
        },
        {
          "actor_name": null,
          "created_at": "2021-06-17T12:03:01",
          "type": "head_ref_force_pushed"
        },
        {
          "actor_name": "Trey Pendragon",
          "created_at": "2021-06-17T12:05:27",
          "type": "deployed"
        },
        {
          "actor_name": null,
          "created_at": "2021-06-17T12:08:11",
          "type": "referenced"
        },
        {
          "actor_name": null,
          "created_at": "2021-06-17T12:08:11",
          "type": "merged"
        },
        {
          "actor_name": null,
          "created_at": "2021-06-17T12:08:11",
          "type": "closed"
        },
        {
          "actor_name": null,
          "created_at": "2021-06-17T12:08:11",
          "type": "head_ref_deleted"
        }
      ],
      "pr_html_url": "https://github.com/pulibrary/lib_jobs/pull/196",
      "action": "pull_request_closed"
    },
    {
      "created_at": "2021-05-04T17:20:50",
      "updated_at": "2021-05-04T17:20:50",
      "html_url": "https://github.com/pulibrary/lib_jobs/issues/159",
      "number": 159,
      "pull_request_html_url": null,
      "repository_html_url": "https://github.com/pulibrary/lib_jobs",
      "repository_name": "lib_jobs",
      "state": "closed",
      "title": "When there is an invoice error we need to create a tab delimitated file",
      "user_name": "carolyncole",
      "comments": [
        {
          "user_name": "carolyncole",
          "updated_at": "2021-06-17T12:16:07",
          "html_url": "https://github.com/pulibrary/lib_jobs/issues/159#issuecomment-863189091",
          "body": "fixed by 934992f"
        }
      ],
      "events": [
        {
          "actor_name": null,
          "created_at": "2021-06-17T12:16:07",
          "type": "closed"
        }
      ],
      "pr_html_url": null,
      "action": "closed"
    },
    {
      "created_at": "2021-02-17T19:32:40",
      "updated_at": "2021-02-17T19:32:40",
      "html_url": "https://github.com/pulibrary/lib_jobs/issues/67",
      "number": 67,
      "pull_request_html_url": null,
      "repository_html_url": "https://github.com/pulibrary/lib_jobs",
      "repository_name": "lib_jobs",
      "state": "closed",
      "title": "Create AlmaVoucher Job",
      "user_name": "carolyncole",
      "comments": [
        {
          "user_name": "carolyncole",
          "updated_at": "2021-06-17T12:16:29",
          "html_url": "https://github.com/pulibrary/lib_jobs/issues/67#issuecomment-863189360",
          "body": "fixed by 934992f"
        }
      ],
      "events": [
        {
          "actor_name": null,
          "created_at": "2021-06-17T12:16:30",
          "type": "closed"
        }
      ],
      "pr_html_url": null,
      "action": "closed"
    },
    {
      "created_at": "2021-06-17T18:46:17",
      "updated_at": "2021-06-17T18:46:17",
      "html_url": "https://github.com/pulibrary/lib_jobs/pull/198",
      "number": 198,
      "pull_request_html_url": "https://github.com/pulibrary/lib_jobs/pull/198",
      "repository_html_url": "https://github.com/pulibrary/lib_jobs",
      "repository_name": "lib_jobs",
      "state": "closed",
      "title": "Adding Alma Fund Adjustment job",
      "user_name": "carolyncole",
      "comments": [],
      "events": [
        {
          "actor_name": null,
          "created_at": "2021-06-17T19:49:16",
          "type": "head_ref_force_pushed"
        },
        {
          "actor_name": "Kevin Reiss",
          "created_at": "2021-06-17T20:45:40",
          "type": "referenced"
        },
        {
          "actor_name": "Kevin Reiss",
          "created_at": "2021-06-17T20:45:40",
          "type": "merged"
        },
        {
          "actor_name": "Kevin Reiss",
          "created_at": "2021-06-17T20:45:40",
          "type": "closed"
        },
        {
          "actor_name": "Kevin Reiss",
          "created_at": "2021-06-17T20:45:40",
          "type": "head_ref_deleted"
        }
      ],
      "pr_html_url": "https://github.com/pulibrary/lib_jobs/pull/198",
      "action": "pull_request_closed"
    }
  ],
  "nomisma": [
    {
      "created_at": "2021-06-16T21:00:12",
      "updated_at": "2021-06-16T21:00:12",
      "html_url": "https://github.com/pulibrary/nomisma/pull/37",
      "number": 37,
      "pull_request_html_url": "https://github.com/pulibrary/nomisma/pull/37",
      "repository_html_url": "https://github.com/pulibrary/nomisma",
      "repository_name": "nomisma",
      "state": "open",
      "title": "Migrate to ruby",
      "user_name": "Kevin McElwee",
      "comments": [],
      "events": [],
      "pr_html_url": "https://github.com/pulibrary/nomisma/pull/37",
      "action": "pull_request_open"
    },
    {
      "created_at": "2021-06-15T23:49:56",
      "updated_at": "2021-06-15T23:49:56",
      "html_url": "https://github.com/pulibrary/nomisma/issues/35",
      "number": 35,
      "pull_request_html_url": null,
      "repository_html_url": "https://github.com/pulibrary/nomisma",
      "repository_name": "nomisma",
      "state": "closed",
      "title": "Spike on the possibility of having a cron job combined with Google Sheets",
      "user_name": "Kevin McElwee",
      "comments": [
        {
          "user_name": "Kevin McElwee",
          "updated_at": "2021-06-17T20:43:22",
          "html_url": "https://github.com/pulibrary/nomisma/issues/35#issuecomment-863551015",
          "body": "Team discussed. Given the infrequency of the update and possible integration with Figgy, it shouldn't be pursued."
        }
      ],
      "events": [
        {
          "actor_name": "Kevin McElwee",
          "created_at": "2021-06-17T20:43:22",
          "type": "closed"
        }
      ],
      "pr_html_url": null,
      "action": "closed"
    },
    {
      "created_at": "2020-08-07T16:30:58",
      "updated_at": "2020-08-07T16:30:58",
      "html_url": "https://github.com/pulibrary/nomisma/issues/6",
      "number": 6,
      "pull_request_html_url": null,
      "repository_html_url": "https://github.com/pulibrary/nomisma",
      "repository_name": "nomisma",
      "state": "closed",
      "title": "Add RDF artifact to Actions",
      "user_name": "Kevin McElwee",
      "comments": [
        {
          "user_name": "Kevin McElwee",
          "updated_at": "2021-06-17T20:43:50",
          "html_url": "https://github.com/pulibrary/nomisma/issues/6#issuecomment-863551264",
          "body": "DRDS team is not comfortable utilizing Actions right now"
        }
      ],
      "events": [
        {
          "actor_name": "Kevin McElwee",
          "created_at": "2021-06-17T20:43:50",
          "type": "closed"
        }
      ],
      "pr_html_url": null,
      "action": "closed"
    },
    {
      "created_at": "2020-08-07T16:35:05",
      "updated_at": "2020-08-07T16:35:05",
      "html_url": "https://github.com/pulibrary/nomisma/issues/8",
      "number": 8,
      "pull_request_html_url": null,
      "repository_html_url": "https://github.com/pulibrary/nomisma",
      "repository_name": "nomisma",
      "state": "closed",
      "title": "Make simple data pipeline flowchart",
      "user_name": "Kevin McElwee",
      "comments": [
        {
          "user_name": "Kevin McElwee",
          "updated_at": "2021-06-17T20:44:07",
          "html_url": "https://github.com/pulibrary/nomisma/issues/8#issuecomment-863551424",
          "body": "The workflow is simple enough that makes this unnecessary"
        }
      ],
      "events": [
        {
          "actor_name": "Kevin McElwee",
          "created_at": "2021-06-17T20:44:07",
          "type": "closed"
        }
      ],
      "pr_html_url": null,
      "action": "closed"
    },
    {
      "created_at": "2020-08-24T14:13:49",
      "updated_at": "2020-08-24T14:13:49",
      "html_url": "https://github.com/pulibrary/nomisma/issues/14",
      "number": 14,
      "pull_request_html_url": null,
      "repository_html_url": "https://github.com/pulibrary/nomisma",
      "repository_name": "nomisma",
      "state": "closed",
      "title": "Add GitHub Actions to bots that can scrape Figgy",
      "user_name": "Kevin McElwee",
      "comments": [
        {
          "user_name": "Kevin McElwee",
          "updated_at": "2021-06-17T20:44:34",
          "html_url": "https://github.com/pulibrary/nomisma/issues/14#issuecomment-863551637",
          "body": "This is unnecessary, we're no longer scraping Figgy, and this process will not be automated."
        }
      ],
      "events": [
        {
          "actor_name": "Kevin McElwee",
          "created_at": "2021-06-17T20:44:34",
          "type": "closed"
        }
      ],
      "pr_html_url": null,
      "action": "closed"
    },
    {
      "created_at": "2021-06-17T20:47:24",
      "updated_at": "2021-06-17T20:47:24",
      "html_url": "https://github.com/pulibrary/nomisma/issues/38",
      "number": 38,
      "pull_request_html_url": null,
      "repository_html_url": "https://github.com/pulibrary/nomisma",
      "repository_name": "nomisma",
      "state": "open",
      "title": "Translate to ruby",
      "user_name": "Kevin McElwee",
      "comments": [],
      "events": [
        {
          "actor_name": "Kevin McElwee",
          "created_at": "2021-06-17T20:47:24",
          "type": "assigned"
        }
      ],
      "pr_html_url": null,
      "action": "created"
    },
    {
      "created_at": "2021-06-16T19:08:23",
      "updated_at": "2021-06-16T19:08:23",
      "html_url": "https://github.com/pulibrary/nomisma/issues/36",
      "number": 36,
      "pull_request_html_url": null,
      "repository_html_url": "https://github.com/pulibrary/nomisma",
      "repository_name": "nomisma",
      "state": "open",
      "title": "Current system does not recognize deleted coins",
      "user_name": "Kevin McElwee",
      "comments": [
        {
          "user_name": "Kevin McElwee",
          "updated_at": "2021-06-17T20:49:46",
          "html_url": "https://github.com/pulibrary/nomisma/issues/36#issuecomment-863554041",
          "body": "Allow \"coin_list\" to be fed into the CoinCollection class. This prevents duplication or batch folders. We can just select the JSON files with the matching filenames."
        }
      ],
      "events": [],
      "pr_html_url": null,
      "action": "updated"
    }
  ],
  "orangelight": [
    {
      "created_at": "2021-06-04T13:50:22",
      "updated_at": "2021-06-04T13:50:22",
      "html_url": "https://github.com/pulibrary/orangelight/issues/2491",
      "number": 2491,
      "pull_request_html_url": null,
      "repository_html_url": "https://github.com/pulibrary/orangelight",
      "repository_name": "orangelight",
      "state": "open",
      "title": "Digitization Requests should still be viewable in orangelight instead of forcing the user to go to Illiad",
      "user_name": "carolyncole",
      "comments": [],
      "events": [
        {
          "actor_name": "Trey Pendragon",
          "created_at": "2021-06-16T22:56:13",
          "type": "assigned"
        }
      ],
      "pr_html_url": null,
      "action": "updated"
    },
    {
      "created_at": "2021-05-13T14:37:47",
      "updated_at": "2021-05-13T14:37:47",
      "html_url": "https://github.com/pulibrary/orangelight/issues/2519",
      "number": 2519,
      "pull_request_html_url": null,
      "repository_html_url": "https://github.com/pulibrary/orangelight",
      "repository_name": "orangelight",
      "state": "open",
      "title": "Create a feature switch for the \"where to find it\" link",
      "user_name": "hackartisan",
      "comments": [],
      "events": [
        {
          "actor_name": "Christina Chortaria",
          "created_at": "2021-06-17T14:01:16",
          "type": "transferred"
        }
      ],
      "pr_html_url": null,
      "action": "updated"
    },
    {
      "created_at": "2021-06-16T16:22:35",
      "updated_at": "2021-06-16T16:22:35",
      "html_url": "https://github.com/pulibrary/orangelight/pull/2515",
      "number": 2515,
      "pull_request_html_url": "https://github.com/pulibrary/orangelight/pull/2515",
      "repository_html_url": "https://github.com/pulibrary/orangelight",
      "repository_name": "orangelight",
      "state": "closed",
      "title": "Allow call numbers to go through the load balancer",
      "user_name": "Christina Chortaria",
      "comments": [],
      "events": [
        {
          "actor_name": "Christina Chortaria",
          "created_at": "2021-06-17T14:11:25",
          "type": "referenced"
        },
        {
          "actor_name": "Christina Chortaria",
          "created_at": "2021-06-17T14:11:25",
          "type": "merged"
        },
        {
          "actor_name": "Christina Chortaria",
          "created_at": "2021-06-17T14:11:25",
          "type": "closed"
        },
        {
          "actor_name": "Christina Chortaria",
          "created_at": "2021-06-17T14:11:25",
          "type": "head_ref_deleted"
        }
      ],
      "pr_html_url": "https://github.com/pulibrary/orangelight/pull/2515",
      "action": "pull_request_closed"
    },
    {
      "created_at": "2021-06-17T15:55:50",
      "updated_at": "2021-06-17T15:55:50",
      "html_url": "https://github.com/pulibrary/orangelight/issues/2520",
      "number": 2520,
      "pull_request_html_url": null,
      "repository_html_url": "https://github.com/pulibrary/orangelight",
      "repository_name": "orangelight",
      "state": "open",
      "title": "Rake task to migrate voyager IDs to alma IDs in figgy",
      "user_name": "hackartisan",
      "comments": [],
      "events": [
        {
          "actor_name": null,
          "created_at": "2021-06-17T15:55:50",
          "type": "labeled"
        }
      ],
      "pr_html_url": null,
      "action": "created"
    },
    {
      "created_at": "2021-06-16T18:05:03",
      "updated_at": "2021-06-16T18:05:03",
      "html_url": "https://github.com/pulibrary/orangelight/pull/2517",
      "number": 2517,
      "pull_request_html_url": "https://github.com/pulibrary/orangelight/pull/2517",
      "repository_html_url": "https://github.com/pulibrary/orangelight",
      "repository_name": "orangelight",
      "state": "closed",
      "title": "Search for Alma equivalent IDs for bookmark display.",
      "user_name": "Trey Pendragon",
      "comments": [
        {
          "user_name": "Coveralls",
          "updated_at": "2021-06-17T16:30:59",
          "html_url": "https://github.com/pulibrary/orangelight/pull/2517#issuecomment-863387686",
          "body": "\n[![Coverage Status](https://coveralls.io/builds/40676431/badge)](https://coveralls.io/builds/40676431)\n\nCoverage decreased (-0.02%) to 96.756% when pulling **3c1a347056fa41ec123dba3c03cce34689597eb6 on bookmark_display** into **8dd530d9fad54e58561421652f8697ab366ebad2 on alma**.\n"
        }
      ],
      "events": [
        {
          "actor_name": "Trey Pendragon",
          "created_at": "2021-06-17T16:19:49",
          "type": "review_requested"
        },
        {
          "actor_name": null,
          "created_at": "2021-06-17T17:58:14",
          "type": "referenced"
        },
        {
          "actor_name": null,
          "created_at": "2021-06-17T17:58:14",
          "type": "merged"
        },
        {
          "actor_name": null,
          "created_at": "2021-06-17T17:58:15",
          "type": "closed"
        },
        {
          "actor_name": null,
          "created_at": "2021-06-17T17:58:15",
          "type": "head_ref_deleted"
        }
      ],
      "pr_html_url": "https://github.com/pulibrary/orangelight/pull/2517",
      "action": "pull_request_closed"
    },
    {
      "created_at": "2021-05-21T19:10:43",
      "updated_at": "2021-05-21T19:10:43",
      "html_url": "https://github.com/pulibrary/orangelight/pull/2469",
      "number": 2469,
      "pull_request_html_url": "https://github.com/pulibrary/orangelight/pull/2469",
      "repository_html_url": "https://github.com/pulibrary/orangelight",
      "repository_name": "orangelight",
      "state": "open",
      "title": "Alma branch",
      "user_name": "carolyncole",
      "comments": [
        {
          "user_name": "Coveralls",
          "updated_at": "2021-06-17T18:12:47",
          "html_url": "https://github.com/pulibrary/orangelight/pull/2469#issuecomment-846219200",
          "body": "\n[![Coverage Status](https://coveralls.io/builds/40679456/badge)](https://coveralls.io/builds/40679456)\n\nCoverage increased (+0.02%) to 96.756% when pulling **bf0b2daab24b7a3739586ef1d993dd5f494ae917 on alma** into **c099150eed8d71bd547d1990ba38518f50ff6da0 on main**.\n"
        }
      ],
      "events": [],
      "pr_html_url": "https://github.com/pulibrary/orangelight/pull/2469",
      "action": "pull_request_open"
    },
    {
      "created_at": "2021-05-27T14:37:43",
      "updated_at": "2021-05-27T14:37:43",
      "html_url": "https://github.com/pulibrary/orangelight/issues/2480",
      "number": 2480,
      "pull_request_html_url": null,
      "repository_html_url": "https://github.com/pulibrary/orangelight",
      "repository_name": "orangelight",
      "state": "open",
      "title": "Update call number browse page",
      "user_name": "Christina Chortaria",
      "comments": [],
      "events": [
        {
          "actor_name": null,
          "created_at": "2021-06-17T19:50:37",
          "type": "labeled"
        },
        {
          "actor_name": null,
          "created_at": "2021-06-17T19:50:45",
          "type": "unlabeled"
        }
      ],
      "pr_html_url": null,
      "action": "updated"
    },
    {
      "created_at": "2021-04-06T15:26:54",
      "updated_at": "2021-04-06T15:26:54",
      "html_url": "https://github.com/pulibrary/orangelight/issues/2396",
      "number": 2396,
      "pull_request_html_url": null,
      "repository_html_url": "https://github.com/pulibrary/orangelight",
      "repository_name": "orangelight",
      "state": "open",
      "title": "Fix availability indexing bots spec",
      "user_name": "Eliot Jordan",
      "comments": [],
      "events": [],
      "pr_html_url": null,
      "action": "updated"
    },
    {
      "created_at": "2021-04-06T15:52:35",
      "updated_at": "2021-04-06T15:52:35",
      "html_url": "https://github.com/pulibrary/orangelight/issues/2398",
      "number": 2398,
      "pull_request_html_url": null,
      "repository_html_url": "https://github.com/pulibrary/orangelight",
      "repository_name": "orangelight",
      "state": "open",
      "title": "Fix CDL availability test",
      "user_name": "Eliot Jordan",
      "comments": [],
      "events": [],
      "pr_html_url": null,
      "action": "updated"
    },
    {
      "created_at": "2021-04-06T15:51:12",
      "updated_at": "2021-04-06T15:51:12",
      "html_url": "https://github.com/pulibrary/orangelight/issues/2397",
      "number": 2397,
      "pull_request_html_url": null,
      "repository_html_url": "https://github.com/pulibrary/orangelight",
      "repository_name": "orangelight",
      "state": "open",
      "title": "Remove due date availability test",
      "user_name": "Eliot Jordan",
      "comments": [],
      "events": [
        {
          "actor_name": null,
          "created_at": "2021-06-17T20:00:30",
          "type": "renamed"
        }
      ],
      "pr_html_url": null,
      "action": "updated"
    },
    {
      "created_at": "2021-04-16T20:09:31",
      "updated_at": "2021-04-16T20:09:31",
      "html_url": "https://github.com/pulibrary/orangelight/issues/2417",
      "number": 2417,
      "pull_request_html_url": null,
      "repository_html_url": "https://github.com/pulibrary/orangelight",
      "repository_name": "orangelight",
      "state": "open",
      "title": "Availability not populating for all the search results",
      "user_name": "hackartisan",
      "comments": [
        {
          "user_name": "hackartisan",
          "updated_at": "2021-06-17T20:09:24",
          "html_url": "https://github.com/pulibrary/orangelight/issues/2417#issuecomment-863530346",
          "body": "We think this was fixed, but need to confirm that an item in a temporary location is coming through with the correct availability."
        }
      ],
      "events": [],
      "pr_html_url": null,
      "action": "updated"
    },
    {
      "created_at": "2021-05-14T17:53:01",
      "updated_at": "2021-05-14T17:53:01",
      "html_url": "https://github.com/pulibrary/orangelight/issues/2452",
      "number": 2452,
      "pull_request_html_url": null,
      "repository_html_url": "https://github.com/pulibrary/orangelight",
      "repository_name": "orangelight",
      "state": "open",
      "title": "Timeout error when requesting",
      "user_name": "Eliot Jordan",
      "comments": [],
      "events": [
        {
          "actor_name": "James R. Griffin III",
          "created_at": "2021-06-17T20:14:28",
          "type": "labeled"
        }
      ],
      "pr_html_url": null,
      "action": "updated"
    },
    {
      "created_at": "2020-07-09T21:51:56",
      "updated_at": "2020-07-09T21:51:56",
      "html_url": "https://github.com/pulibrary/orangelight/issues/2156",
      "number": 2156,
      "pull_request_html_url": null,
      "repository_html_url": "https://github.com/pulibrary/orangelight",
      "repository_name": "orangelight",
      "state": "closed",
      "title": "Review Alma Patron Types",
      "user_name": "Kevin Reiss",
      "comments": [],
      "events": [
        {
          "actor_name": null,
          "created_at": "2021-06-17T20:19:53",
          "type": "closed"
        }
      ],
      "pr_html_url": null,
      "action": "closed"
    },
    {
      "created_at": "2020-10-20T15:53:28",
      "updated_at": "2020-10-20T15:53:28",
      "html_url": "https://github.com/pulibrary/orangelight/issues/2305",
      "number": 2305,
      "pull_request_html_url": null,
      "repository_html_url": "https://github.com/pulibrary/orangelight",
      "repository_name": "orangelight",
      "state": "closed",
      "title": "Create an approved wireframe for a modified coin show page",
      "user_name": "Kevin McElwee",
      "comments": [],
      "events": [
        {
          "actor_name": "Kevin McElwee",
          "created_at": "2021-06-17T20:40:54",
          "type": "closed"
        }
      ],
      "pr_html_url": null,
      "action": "closed"
    }
  ],
  "princeton_ansible": [
    {
      "created_at": "2021-06-16T17:46:33",
      "updated_at": "2021-06-16T17:46:33",
      "html_url": "https://github.com/pulibrary/princeton_ansible/pull/2321",
      "number": 2321,
      "pull_request_html_url": "https://github.com/pulibrary/princeton_ansible/pull/2321",
      "repository_html_url": "https://github.com/pulibrary/princeton_ansible",
      "repository_name": "princeton_ansible",
      "state": "closed",
      "title": "[Orangelight] Point alma-qa database to qa database.",
      "user_name": "Trey Pendragon",
      "comments": [],
      "events": [
        {
          "actor_name": "Christina Chortaria",
          "created_at": "2021-06-17T13:30:00",
          "type": "referenced"
        },
        {
          "actor_name": "Christina Chortaria",
          "created_at": "2021-06-17T13:30:00",
          "type": "merged"
        },
        {
          "actor_name": "Christina Chortaria",
          "created_at": "2021-06-17T13:30:00",
          "type": "closed"
        },
        {
          "actor_name": "Christina Chortaria",
          "created_at": "2021-06-17T13:30:01",
          "type": "head_ref_deleted"
        }
      ],
      "pr_html_url": "https://github.com/pulibrary/princeton_ansible/pull/2321",
      "action": "pull_request_closed"
    },
    {
      "created_at": "2021-06-15T20:59:17",
      "updated_at": "2021-06-15T20:59:17",
      "html_url": "https://github.com/pulibrary/princeton_ansible/issues/2315",
      "number": 2315,
      "pull_request_html_url": null,
      "repository_html_url": "https://github.com/pulibrary/princeton_ansible",
      "repository_name": "princeton_ansible",
      "state": "open",
      "title": "Create a VM for bibdata-alma-worker-staging",
      "user_name": "Christina Chortaria",
      "comments": [],
      "events": [
        {
          "actor_name": null,
          "created_at": "2021-06-17T15:48:15",
          "type": "labeled"
        }
      ],
      "pr_html_url": null,
      "action": "updated"
    },
    {
      "created_at": "2021-06-17T16:51:38",
      "updated_at": "2021-06-17T16:51:38",
      "html_url": "https://github.com/pulibrary/princeton_ansible/pull/2323",
      "number": 2323,
      "pull_request_html_url": "https://github.com/pulibrary/princeton_ansible/pull/2323",
      "repository_html_url": "https://github.com/pulibrary/princeton_ansible",
      "repository_name": "princeton_ansible",
      "state": "open",
      "title": "[Bibdata] Add new S3 configs for partner updates.",
      "user_name": "Trey Pendragon",
      "comments": [],
      "events": [
        {
          "actor_name": "Trey Pendragon",
          "created_at": "2021-06-17T19:02:24",
          "type": "head_ref_force_pushed"
        },
        {
          "actor_name": "Trey Pendragon",
          "created_at": "2021-06-17T19:02:51",
          "type": "review_requested"
        }
      ],
      "pr_html_url": "https://github.com/pulibrary/princeton_ansible/pull/2323",
      "action": "pull_request_open"
    },
    {
      "created_at": "2021-06-17T20:23:48",
      "updated_at": "2021-06-17T20:23:48",
      "html_url": "https://github.com/pulibrary/princeton_ansible/pull/2324",
      "number": 2324,
      "pull_request_html_url": "https://github.com/pulibrary/princeton_ansible/pull/2324",
      "repository_html_url": "https://github.com/pulibrary/princeton_ansible",
      "repository_name": "princeton_ansible",
      "state": "closed",
      "title": "[Figgy] Add ASpace environment variables.",
      "user_name": "Trey Pendragon",
      "comments": [],
      "events": [
        {
          "actor_name": null,
          "created_at": "2021-06-17T20:34:00",
          "type": "referenced"
        },
        {
          "actor_name": null,
          "created_at": "2021-06-17T20:34:00",
          "type": "merged"
        },
        {
          "actor_name": null,
          "created_at": "2021-06-17T20:34:00",
          "type": "closed"
        },
        {
          "actor_name": null,
          "created_at": "2021-06-17T20:34:01",
          "type": "head_ref_deleted"
        }
      ],
      "pr_html_url": "https://github.com/pulibrary/princeton_ansible/pull/2324",
      "action": "pull_request_closed"
    },
    {
      "created_at": "2021-06-17T22:29:59",
      "updated_at": "2021-06-17T22:29:59",
      "html_url": "https://github.com/pulibrary/princeton_ansible/pull/2325",
      "number": 2325,
      "pull_request_html_url": "https://github.com/pulibrary/princeton_ansible/pull/2325",
      "repository_html_url": "https://github.com/pulibrary/princeton_ansible",
      "repository_name": "princeton_ansible",
      "state": "open",
      "title": "[Figgy] Fixes for production run.",
      "user_name": "Trey Pendragon",
      "comments": [],
      "events": [],
      "pr_html_url": "https://github.com/pulibrary/princeton_ansible/pull/2325",
      "action": "pull_request_open"
    }
  ],
  "pul-the-hard-way": [
    {
      "created_at": "2021-06-16T20:02:14",
      "updated_at": "2021-06-16T20:02:14",
      "html_url": "https://github.com/pulibrary/pul-the-hard-way/pull/75",
      "number": 75,
      "pull_request_html_url": "https://github.com/pulibrary/pul-the-hard-way/pull/75",
      "repository_html_url": "https://github.com/pulibrary/pul-the-hard-way",
      "repository_name": "pul-the-hard-way",
      "state": "closed",
      "title": "Create lib-sftp cron job documentation",
      "user_name": "Eliot Jordan",
      "comments": [],
      "events": [
        {
          "actor_name": "Christina Chortaria",
          "created_at": "2021-06-16T23:03:15",
          "type": "referenced"
        },
        {
          "actor_name": "Christina Chortaria",
          "created_at": "2021-06-16T23:03:15",
          "type": "merged"
        },
        {
          "actor_name": "Christina Chortaria",
          "created_at": "2021-06-16T23:03:15",
          "type": "closed"
        }
      ],
      "pr_html_url": "https://github.com/pulibrary/pul-the-hard-way/pull/75",
      "action": "pull_request_closed"
    }
  ],
  "requests": [
    {
      "created_at": "2021-06-15T17:14:31",
      "updated_at": "2021-06-15T17:14:31",
      "html_url": "https://github.com/pulibrary/requests/pull/992",
      "number": 992,
      "pull_request_html_url": "https://github.com/pulibrary/requests/pull/992",
      "repository_html_url": "https://github.com/pulibrary/requests",
      "repository_name": "requests",
      "state": "closed",
      "title": "Updating to allow borrow direct and ILL for Resource shared items",
      "user_name": "carolyncole",
      "comments": [],
      "events": [
        {
          "actor_name": "Kevin Reiss",
          "created_at": "2021-06-17T02:34:33",
          "type": "referenced"
        },
        {
          "actor_name": "Kevin Reiss",
          "created_at": "2021-06-17T02:34:33",
          "type": "merged"
        },
        {
          "actor_name": "Kevin Reiss",
          "created_at": "2021-06-17T02:34:33",
          "type": "closed"
        }
      ],
      "pr_html_url": "https://github.com/pulibrary/requests/pull/992",
      "action": "pull_request_closed"
    },
    {
      "created_at": "2021-05-06T14:02:04",
      "updated_at": "2021-05-06T14:02:04",
      "html_url": "https://github.com/pulibrary/requests/pull/922",
      "number": 922,
      "pull_request_html_url": "https://github.com/pulibrary/requests/pull/922",
      "repository_html_url": "https://github.com/pulibrary/requests",
      "repository_name": "requests",
      "state": "open",
      "title": "Alma",
      "user_name": "Kevin Reiss",
      "comments": [],
      "events": [],
      "pr_html_url": "https://github.com/pulibrary/requests/pull/922",
      "action": "pull_request_open"
    },
    {
      "created_at": "2021-02-05T15:45:26",
      "updated_at": "2021-02-05T15:45:26",
      "html_url": "https://github.com/pulibrary/requests/issues/891",
      "number": 891,
      "pull_request_html_url": null,
      "repository_html_url": "https://github.com/pulibrary/requests",
      "repository_name": "requests",
      "state": "open",
      "title": "Update unavailable_statuses, on_order?, and in_process? to match alma",
      "user_name": "hackartisan",
      "comments": [
        {
          "user_name": "Kevin Reiss",
          "updated_at": "2021-06-17T13:47:46",
          "html_url": "https://github.com/pulibrary/requests/issues/891#issuecomment-863254520",
          "body": "@carolyncole I think we have these two cases handled now. "
        }
      ],
      "events": [
        {
          "actor_name": null,
          "created_at": "2021-06-17T13:47:46",
          "type": "mentioned"
        },
        {
          "actor_name": null,
          "created_at": "2021-06-17T13:47:46",
          "type": "subscribed"
        }
      ],
      "pr_html_url": null,
      "action": "updated"
    },
    {
      "created_at": "2021-06-15T13:44:49",
      "updated_at": "2021-06-15T13:44:49",
      "html_url": "https://github.com/pulibrary/requests/issues/991",
      "number": 991,
      "pull_request_html_url": null,
      "repository_html_url": "https://github.com/pulibrary/requests",
      "repository_name": "requests",
      "state": "open",
      "title": "When the alma holds fails after a ReCAP request is successful email Recap Problems",
      "user_name": "carolyncole",
      "comments": [],
      "events": [
        {
          "actor_name": "Kevin Reiss",
          "created_at": "2021-06-17T13:48:24",
          "type": "labeled"
        }
      ],
      "pr_html_url": null,
      "action": "updated"
    },
    {
      "created_at": "2021-05-28T14:37:26",
      "updated_at": "2021-05-28T14:37:26",
      "html_url": "https://github.com/pulibrary/requests/issues/971",
      "number": 971,
      "pull_request_html_url": null,
      "repository_html_url": "https://github.com/pulibrary/requests",
      "repository_name": "requests",
      "state": "closed",
      "title": "Items in Resource Sharing Request Process Type Should provide Resource Sharing Request Options",
      "user_name": "Kevin Reiss",
      "comments": [],
      "events": [
        {
          "actor_name": "Kevin Reiss",
          "created_at": "2021-06-17T13:48:51",
          "type": "closed"
        }
      ],
      "pr_html_url": null,
      "action": "closed"
    },
    {
      "created_at": "2021-06-17T15:33:54",
      "updated_at": "2021-06-17T15:33:54",
      "html_url": "https://github.com/pulibrary/requests/issues/994",
      "number": 994,
      "pull_request_html_url": null,
      "repository_html_url": "https://github.com/pulibrary/requests",
      "repository_name": "requests",
      "state": "open",
      "title": "Remove Recap from Open Libraries",
      "user_name": "Kevin Reiss",
      "comments": [],
      "events": [
        {
          "actor_name": "Kevin Reiss",
          "created_at": "2021-06-17T15:33:54",
          "type": "labeled"
        }
      ],
      "pr_html_url": null,
      "action": "created"
    },
    {
      "created_at": "2021-06-17T15:34:53",
      "updated_at": "2021-06-17T15:34:53",
      "html_url": "https://github.com/pulibrary/requests/issues/995",
      "number": 995,
      "pull_request_html_url": null,
      "repository_html_url": "https://github.com/pulibrary/requests",
      "repository_name": "requests",
      "state": "open",
      "title": "Close all Campus Libraries",
      "user_name": "Kevin Reiss",
      "comments": [],
      "events": [
        {
          "actor_name": "Kevin Reiss",
          "created_at": "2021-06-17T15:34:53",
          "type": "labeled"
        }
      ],
      "pr_html_url": null,
      "action": "created"
    },
    {
      "created_at": "2021-06-16T14:28:01",
      "updated_at": "2021-06-16T14:28:01",
      "html_url": "https://github.com/pulibrary/requests/pull/993",
      "number": 993,
      "pull_request_html_url": "https://github.com/pulibrary/requests/pull/993",
      "repository_html_url": "https://github.com/pulibrary/requests",
      "repository_name": "requests",
      "state": "open",
      "title": "Extending the Requests::Patron#current_patron method to handle 429 HTTP responses from the BibData endpoint",
      "user_name": "James R. Griffin III",
      "comments": [],
      "events": [
        {
          "actor_name": "James R. Griffin III",
          "created_at": "2021-06-17T17:42:13",
          "type": "convert_to_draft"
        }
      ],
      "pr_html_url": "https://github.com/pulibrary/requests/pull/993",
      "action": "pull_request_open"
    },
    {
      "created_at": "2021-06-17T16:07:12",
      "updated_at": "2021-06-17T16:07:12",
      "html_url": "https://github.com/pulibrary/requests/pull/997",
      "number": 997,
      "pull_request_html_url": "https://github.com/pulibrary/requests/pull/997",
      "repository_html_url": "https://github.com/pulibrary/requests",
      "repository_name": "requests",
      "state": "open",
      "title": "Removes Copy 0, fixes #i986",
      "user_name": "Shaun Ellis",
      "comments": [
        {
          "user_name": "Shaun Ellis",
          "updated_at": "2021-06-17T18:55:36",
          "html_url": "https://github.com/pulibrary/requests/pull/997#issuecomment-863486626",
          "body": "@kevinreiss this should be ready for review."
        }
      ],
      "events": [
        {
          "actor_name": "Kevin Reiss",
          "created_at": "2021-06-17T18:55:36",
          "type": "mentioned"
        },
        {
          "actor_name": "Kevin Reiss",
          "created_at": "2021-06-17T18:55:36",
          "type": "subscribed"
        }
      ],
      "pr_html_url": "https://github.com/pulibrary/requests/pull/997",
      "action": "pull_request_open"
    },
    {
      "created_at": "2021-06-09T22:39:38",
      "updated_at": "2021-06-09T22:39:38",
      "html_url": "https://github.com/pulibrary/requests/issues/987",
      "number": 987,
      "pull_request_html_url": null,
      "repository_html_url": "https://github.com/pulibrary/requests",
      "repository_name": "requests",
      "state": "open",
      "title": "Enumeration Sort is Off",
      "user_name": "Kevin Reiss",
      "comments": [],
      "events": [
        {
          "actor_name": "Shaun Ellis",
          "created_at": "2021-06-17T19:43:36",
          "type": "assigned"
        }
      ],
      "pr_html_url": null,
      "action": "updated"
    },
    {
      "created_at": "2021-06-17T15:35:50",
      "updated_at": "2021-06-17T15:35:50",
      "html_url": "https://github.com/pulibrary/requests/issues/996",
      "number": 996,
      "pull_request_html_url": null,
      "repository_html_url": "https://github.com/pulibrary/requests",
      "repository_name": "requests",
      "state": "open",
      "title": "Update Help Met Get It Labeling for Form to reflect specifics of of the Alma Migration",
      "user_name": "Kevin Reiss",
      "comments": [
        {
          "user_name": "Kevin Reiss",
          "updated_at": "2021-06-17T20:42:50",
          "html_url": "https://github.com/pulibrary/requests/issues/996#issuecomment-863550725",
          "body": "Complete along with #994 "
        }
      ],
      "events": [
        {
          "actor_name": "Kevin Reiss",
          "created_at": "2021-06-17T15:35:50",
          "type": "labeled"
        }
      ],
      "pr_html_url": null,
      "action": "created"
    },
    {
      "created_at": "2021-06-17T21:32:35",
      "updated_at": "2021-06-17T21:32:35",
      "html_url": "https://github.com/pulibrary/requests/issues/998",
      "number": 998,
      "pull_request_html_url": null,
      "repository_html_url": "https://github.com/pulibrary/requests",
      "repository_name": "requests",
      "state": "open",
      "title": "Serial Record Displays Available Copies as Unavailable",
      "user_name": "Kevin Reiss",
      "comments": [
        {
          "user_name": "Kevin Reiss",
          "updated_at": "2021-06-17T21:37:39",
          "html_url": "https://github.com/pulibrary/requests/issues/998#issuecomment-863580997",
          "body": "Seems to be a global issue with records with enumerated materials - https://catalog-alma-qa.princeton.edu/requests/995642093506421?mfhd=22167825780006421&source=pulsearch"
        }
      ],
      "events": [],
      "pr_html_url": null,
      "action": "created"
    }
  ],
  "researchdata": [
    {
      "created_at": "2021-06-17T11:38:50",
      "updated_at": "2021-06-17T11:38:50",
      "html_url": "https://github.com/pulibrary/researchdata/pull/91",
      "number": 91,
      "pull_request_html_url": "https://github.com/pulibrary/researchdata/pull/91",
      "repository_html_url": "https://github.com/pulibrary/researchdata",
      "repository_name": "researchdata",
      "state": "open",
      "title": "Bump postcss from 7.0.35 to 7.0.36 in /core",
      "user_name": "dependabot[bot]",
      "comments": [],
      "events": [
        {
          "actor_name": null,
          "created_at": "2021-06-17T11:38:51",
          "type": "labeled"
        },
        {
          "actor_name": null,
          "created_at": "2021-06-17T11:38:51",
          "type": "labeled"
        }
      ],
      "pr_html_url": "https://github.com/pulibrary/researchdata/pull/91",
      "action": "pull_request_open"
    },
    {
      "created_at": "2021-05-12T09:51:58",
      "updated_at": "2021-05-12T09:51:58",
      "html_url": "https://github.com/pulibrary/researchdata/pull/83",
      "number": 83,
      "pull_request_html_url": "https://github.com/pulibrary/researchdata/pull/83",
      "repository_html_url": "https://github.com/pulibrary/researchdata",
      "repository_name": "researchdata",
      "state": "closed",
      "title": "Bump postcss from 7.0.35 to 8.2.10 in /core",
      "user_name": "dependabot[bot]",
      "comments": [
        {
          "user_name": "dependabot[bot]",
          "updated_at": "2021-06-17T11:38:53",
          "html_url": "https://github.com/pulibrary/researchdata/pull/83#issuecomment-863166288",
          "body": "Superseded by #91."
        }
      ],
      "events": [
        {
          "actor_name": null,
          "created_at": "2021-06-17T11:38:54",
          "type": "closed"
        },
        {
          "actor_name": null,
          "created_at": "2021-06-17T11:38:55",
          "type": "head_ref_deleted"
        }
      ],
      "pr_html_url": "https://github.com/pulibrary/researchdata/pull/83",
      "action": "pull_request_closed"
    },
    {
      "created_at": "2021-06-17T16:58:34",
      "updated_at": "2021-06-17T16:58:34",
      "html_url": "https://github.com/pulibrary/researchdata/pull/92",
      "number": 92,
      "pull_request_html_url": "https://github.com/pulibrary/researchdata/pull/92",
      "repository_html_url": "https://github.com/pulibrary/researchdata",
      "repository_name": "researchdata",
      "state": "open",
      "title": "Bump postcss from 7.0.32 to 7.0.36 in /themes/custom/prds",
      "user_name": "dependabot[bot]",
      "comments": [],
      "events": [
        {
          "actor_name": null,
          "created_at": "2021-06-17T16:58:35",
          "type": "labeled"
        },
        {
          "actor_name": null,
          "created_at": "2021-06-17T16:58:35",
          "type": "labeled"
        }
      ],
      "pr_html_url": "https://github.com/pulibrary/researchdata/pull/92",
      "action": "pull_request_open"
    }
  ],
  "__meta__": {
    "issue_count": 102,
    "closed_count": 28,
    "created_count": 14,
    "pull_request_closed_count": 16,
    "pull_request_open_count": 14,
    "updated_count": 30,
    "today": "2021-06-17T22:00:05",
    "yesterday": "2021-06-16T22:00:05"
  }
}